Workbook

Sheet 0. Intro
B1: English
B2: ='12.lan'!D4 -> BALANCE SHEET CALCULATOR | M2: =IF('12.lan'!B2="","",'12.lan'!B2) -> Select your language
B3: ='12.lan'!D6 -> Version | C3: 5.06 | M3: =IF('12.lan'!B3="","",'12.lan'!B3) -> Deutsch
M4: =IF('12.lan'!B4="","",'12.lan'!B4) -> Italiano
B5: ='12.lan'!D7 -> WELCOME! | M5: =IF('12.lan'!B5="","",'12.lan'!B5) -> English
B6: ='12.lan'!D8 -> This tool is for calculating the overall Common Good Points for your company or organisation. It complements the Common Good Report and has to be used together with it. Have fun with your calculation! | M6: =IF('12.lan'!B6="","",'12.lan'!B6) -> Español
M7: =IF('12.lan'!B7="","",'12.lan'!B7) -> Francais
B8: ='12.lan'!D9 -> HOW TO USE THE BALANCE SHEET CALCULATOR: | M8: =IF('12.lan'!B8="","",'12.lan'!B8)
B9: ='12.lan'!D10 -> 1. General | D9: ='12.lan'!D11 -> You can enter general information about your company or organisation in this section. | M9: =IF('12.lan'!B9="","",'12.lan'!B9)
B10: ='12.lan'!D28 -> 2. Company details | D10: ='12.lan'!D12 -> All fields in this section must be completed as they are essential for the weighting of each theme. | M10: =IF('12.lan'!B10="","",'12.lan'!B10)
B11: ='12.lan'!D29 -> 3. Scoring | D11: ='12.lan'!D13 -> For each theme (A1, B1, ...) a certain maximum number of Common Good Points can be achieved. To evaluate how many points your company scores, follow these steps: | M11: =IF('12.lan'!B11="","",'12.lan'!B11)
B12: a) | D12: ='12.lan'!D14 -> Describe the current status and potential for improvement for the various aspects under key headings. Use the workbook as a reference. (This is optional and not absolutely necessary for the calculation.) | M12: =IF('12.lan'!B12="","",'12.lan'!B12)
B13: b) | D13: ='12.lan'!D15 -> Based on these descriptions, indicate on a scale of 0-10 how far you consider the respective aspect is met (Achievement level). The criteria for choosing the correct value can be found in the Workbook.
B14: c) | D14: ='12.lan'!D16 -> Negative aspects are allocated negative points according to the descriptions set out in the Workbook.
B15: d) | D15: ='12.lan'!D17 -> Where deemed necessary for your company and in agreement with the auditors you can change the relative weightings of individual aspects (A1.1, A1.2, ..). In the column Weighting, you can select values for each aspect. The distribution of available points for individual aspects will then be adjusted automatically, so that the total of all aspects of an indicator result in 100%.
B16: e) | D16: ='12.lan'!D18 -> The calculation automatically weights each theme’s total value against the data in the ‘Company details’ section and rounds it to a whole-number multiple of 10%.
B17: f) | D17: ='12.lan'!D45 -> The format of the numbers is usually rounded to facilitate the visualization but the numbers are not actually rounded. You may see for example that an aspect is 1 (real value 1,3) and other 1 (real value 1,4) but the sum of the two aspects is 3 (real value 2,7)
B18: ='12.lan'!D30 -> 4. ECG Matrix | D18: ='12.lan'!D19 -> The ECG-Matrix displays your result in a table.
B19: ='12.lan'!D31 -> 5. Values star | D19: ='12.lan'!D21 -> The values-star displays your result arranged by value as a graphic.
B20: ='12.lan'!D32 -> 6. Group star | D20: ='12.lan'!D22 -> The group-star displays your result arranged by stakeholder as a graphic.
B21: ='12.lan'!D33 -> 7. Theme star | D21: ='12.lan'!D23 -> The theme-star displays the result of your themes as a graphic.
B22: ='12.lan'!D34 -> 8. Weighting model description | D22: ='12.lan'!D24 -> This is a description of the weighting model.
B23: ='12.lan'!D35 -> 9. Weighting (hidden) | D23: ='12.lan'!D25 -> This is where the calculation determines how the individual stakeholder groups and themes are weighted.
B24: ='12.lan'!D36 -> 10. Industry sectors (hidden) | D24: ='12.lan'!D26 -> This contains an assessment of the relevance of supply chains and environmental sustainability for all industry sectors, used in the weighting.
B25: ='12.lan'!D37 -> 11. Countries (hidden) | D25: ='12.lan'!D27 -> This contains statistics for countries and regions used in the weighting.
B27: ='12.lan'!D40 -> KEY
B28: ='12.lan'!D41 -> Field is editable (green frame, dark green text)
B30: ='12.lan'!D42 -> Feld is read-only (grey frame, dark grey text)
B32: ='12.lan'!D43 -> non valid value entry (for correct calculation change value)
B34: ='12.lan'!D54 -> CONTACT
B35: ='12.lan'!D55 -> Questions regarding preparation of balance sheet: beratung@gemeinwohl-oekonomie.org (GWÖ-BeraterInnen);
B36: ='12.lan'!D56 -> Questions regarding audit: audit@gemeinwohl-oekonomie.org (GWÖ-AuditorInnen);
B37: ='12.lan'!D57 -> Feedback on the development of the Matrix: bilanz@ecogood.org (Matrix Development Team)
B38: ='12.lan'!D58 -> Excel programming: Christian Loy (christian.loy@gmx.at); Christian Kozina; Multilanguage tool: Bernhard Oberrauch
B39: ='12.lan'!D59 -> Contents: ECG-Matrix Development Team
B41: ='12.lan'!D60 -> NOTES
B42: ='12.lan'!D61 -> All sheets are optimised for printing on A4 format (landscape or portrait). The height of rows can be adjusted, if you enter more text The format of the numbers is usually rounded to facilitate the visualization but the numbers are not actually rounded. You may see as an example that an aspect is 1 (actually 1,3) and other 1 (actually 1,4) but the sum is 3 (actually 2,7).

Sheet 1. General
B2: ='12.lan'!D91&" - "&'0. Intro'!B3&" "&'0. Intro'!C3 -> Common Good Balance Calculator - Version 5.06
B3: ='12.lan'!D62 -> GENERAL INFORMATION ABOUT THE COMPANY
B4: ='12.lan'!D63 -> Please complete all fields.
B6: ='12.lan'!D64 -> Name of Company / Organisation: | C6: LuftGewinn
B7: ='12.lan'!D65 -> Address: | C7: , , 45456
B8: ='12.lan'!D66 -> Country: | C8: Deutschland
B9: ='12.lan'!D67 -> Industry sector:
B10: ='12.lan'!D68 -> Website: | C10: www.a.qq
B12: ='12.lan'!D83 -> Period under review | C12: 01.01.2019 - 31.12.2019
B14: ='12.lan'!D73 -> Document created by: | C14: N. nachar
B15: ='12.lan'!D74 -> Email address: | C15: nachar@gmx.net
B16: ='12.lan'!D75 -> Phone number:
B18: ='12.lan'!D76 -> Consultant:
B19: ='12.lan'!D74 -> Email address:
B20: ='12.lan'!D75 -> Phone number:
B22: ='12.lan'!D79 -> Short description of Company / Organisation | C22: gggg
B24: ='12.lan'!D80 -> Additional comments:

Sheet 2. Company Facts
B2: ='12.lan'!D91&" - "&'0. Intro'!B3&" "&'0. Intro'!C3 -> Common Good Balance Calculator - Version 5.06 | M2: ='12.lan'!D52 -> yes
B3: ='12.lan'!D194 -> Company details | M3: ='12.lan'!D53 -> no
B4: ='12.lan'!D195 -> Fill in the highlighted fields below. Where detailed information is not available, please enter estimates, otherwise the calculation will not be accurate
B6: ='12.lan'!B108 -> A: Suppliers
B7: ='12.lan'!D297 -> Total purchases from suppliers (in Euros): | C7: 200000 | D7: =IF(SUM(F10:F14)>C7,'12.lan'!D44,"")
B8: ='12.lan'!D298 -> Enter the 5 most important industry sectors whose products or services you use.
B9: ='12.lan'!D299 -> Industry sector | C9: ='12.lan'!D300 -> Description | D9: ='12.lan'!D301 -> Region of origin | F9: ='12.lan'!D302 -> Costs
B10: A - Landwirtschaft, Forstwirtschaft und Fischerei | D10: EGY Ägypten | F10: 3388
B11: Ca - Food production, drinks and tobacco (C10, C11, C12) | D11: AFG Afghanistan | F11: 654
B12: A - Landwirtschaft, Forstwirtschaft und Fischerei | D12: DZA Algerien | F12: 456
B13: A - Landwirtschaft, Forstwirtschaft und Fischerei | D13: BGD Bangladesch | F13: 77
B14: Please enter | F14: 0
B15: ='12.lan'!$D$303 -> Main origin of the other suppliers | D15: QAT Katar | F15: =C7-F10-F11-F12-F13-F14 -> 195425
B17: ='12.lan'!B122 -> B: Owners, equity- and financial service providers
B18: ='12.lan'!D304 -> Profit | C18: 456456456
B19: ='12.lan'!D305 -> Financing costs | C19: 266
B20: ='12.lan'!D306 -> Income from financial investments | C20: 500
B21: ='12.lan'!D307 -> Total assets | C21: 420
B22: ='12.lan'!D308 -> Additions to fixed-assets | C22: 400
B23: ='12.lan'!D309 -> Financial assets and cash balance | C23: 310
B25: ='12.lan'!B137 -> C: Employees
B26: ='12.lan'!D310 -> Number of employees (full time equivalents) | C26: 5
B27: ='12.lan'!D311 -> Staff costs (gross without employer contribution) | C27: 5501
B28: ='12.lan'!D312 -> Enter the 3 countries and regions where most of the staff are
B29: ='12.lan'!D313 -> Country and region | D29: ='12.lan'!D314 -> Amount in %
B30: ETH Äthiopien | D30: 0.46 | E30: =IF(SUM(D30:D32)>"100%","fehlerhafte Eingabe","")
B31: BHR Bahrain | D31: 0.11
D32: 0
B33: ='12.lan'!D315 -> Average journey to work for staff (in km) | C33: 456456
B34: ='12.lan'!D316 -> Is there a canteen for the majority of staff? | C34: no | D34: Ja | F34: Nein
B36: ='12.lan'!B158 -> D: Customers and other companies
B37: ='12.lan'!D317 -> Turnover (in Euros) | C37: 124
B38: ='12.lan'!D318 -> Are your customers mainly other companies? | C38: ja
B39: ='12.lan'!D319 -> Enter the 3 most important industry sectors which your company is active in, including a rough share of turnover
B40: ='12.lan'!D320 -> Industry sector | C40: ='12.lan'!D321 -> Description | D40: ='12.lan'!D322 -> % Amount of total turnover
B41: J - Information und Kommunikation | D41: 0.87 | F41: =IF(SUM(D41:D43)>"100%","fehlerhafte Eingabe","")
B42: Ce - Pharmaceutical products and preparations (C21) | C42: abc | D42: 0.13
B43: Please enter | D43: 0 | F43: =IF(SUM(D41:D43)>1,'12.lan'!D44,"")
B45: ='12.lan'!B175 -> E: Social environment
B46: ='12.lan'!D323 -> Company size | C46: ='9. Weighting'!H39 -> Micro-business

Sheet 3. Calc
B2: ='12.lan'!D91&" - "&'0. Intro'!B3&" "&'0. Intro'!C3 -> Common Good Balance Calculator - Version 5.06
B3: ='12.lan'!D90 -> CALCULATION OF INDIVIDUAL ASPECTS
F4: ='12.lan'!D92 -> Total Balance Score: | H4: =I4/J4 -> -0.38904762 | I4: =IF(SUM(I9+I23+I38+I59+I76)*1000/SUM(J9+J23+J38+J59+J76)<-3600,-3600,SUM(I9+I23+I38+I59+I76)*1000/SUM(J9+J23+J38+J59+J76)) -> -389.04762 | J4: =SUM(J9+J23+J38+J59+J76)*1000/SUM(J9+J23+J38+J59+J76) -> 1000 | L4: ausblenden | O4: ausblenben
B5: ='12.lan'!D82&": "&'1. General'!C6&"; "&'12.lan'!D83&": "&'1. General'!C12 -> Company / Organisation: LuftGewinn; Period under review: 01.01.2019 - 31.12.2019
B8: ='12.lan'!D93 -> No. | C8: ='12.lan'!D107 -> Stakeholders/ Themes/ Aspects | D8: ='12.lan'!D96 -> Weight | F8: ='12.lan'!D102 -> Current status | H8: ='12.lan'!D104 -> Est% | I8: ='12.lan'!D105 -> Points | J8: ='12.lan'!D106 -> Max. | L8: Gewichtung Standard | O8: Reset
B9: A | C9: ='12.lan'!D108 -> Suppliers | D9: =L9 -> 0.5 | E9: =VLOOKUP(D9,$C$102:$D$106,2,FALSE()) -> low | H9: =IFERROR(I9/J9,0) -> -0.875 | I9: =I10+I13+I17+I20 -> -83.333333 | J9: =J10+J13+J17+J20 -> 95.238095 | L9: ='9. Weighting'!K49 -> 0.5 | N9: =IF(D9<>L9,'12.lan'!$D$240&VLOOKUP(L9,$C$102:$D$106,2,FALSE())&" ("&L9&")","")
B10: A1 | C10: ='12.lan'!D109 -> Human dignity in the supply chain | D10: =IF(K10="trifft nicht zu",C106,'9. Weighting'!M16) -> 1 | E10: =VLOOKUP(D10,$C$102:$D$106,2,FALSE()) -> medium | F10: ='9. Weighting'!M16 -> 1 | H10: =IF(J10<>0,SUM(I11:I12)/J10,"-") -> -1.8 | I10: =IF(J10=0,0,H10*J10) -> -42.857143 | J10: ='9. Weighting'!M15 -> 23.809524 | L10: =VLOOKUP(O10,$C$102:$E$106,3,FALSE()) -> 1 | M10: =VLOOKUP(D10,$C$102:$E$106,3,FALSE()) -> 1 | N10: =IF(L10=M10,"",'12.lan'!$D$240&VLOOKUP(L10,$C$102:$D$106,2,FALSE())&" ("&L10&")") | O10: =IF(K10="trifft nicht zu",C106,'9. Weighting'!M16) -> 1
B11: A1.1 | C11: ='12.lan'!D110 -> Working conditions and social impact in the supply chain | F11: ='12.lan'!$D$329 -> Introduce value between 0 and 10 | H11: 2 | I11: =J11*H11/10 -> 4.7619048 | J11: =J10*K11/K11 -> 23.809524 | K11: 1 | N11: =IF(L11=M11,"",'12.lan'!$D$240&" "&VLOOKUP(L11,$C$102:$D$106,2,FALSE())&" ("&L11&")")
B12: A1.2 | C12: ='12.lan'!D111 -> Negative aspect: violation of human dignity in the supply chain | F12: ='12.lan'!$D$330 -> Introduce negative points between 0 and -200 | H12: -100 | I12: =H12*J10/50 -> -47.619048 | J12: =-200*J10/50 -> -95.238095
B13: A2 | C13: ='12.lan'!D112 -> Solidarity and social justice in the supply chain | D13: =IF(K13="trifft nicht zu",C106,'9. Weighting'!N16) -> 1 | E13: =VLOOKUP(D13,$C$102:$D$106,2,FALSE()) -> medium | F13: =IF(K13="trifft nicht zu","trifft nicht zu",'9. Weighting'!N16) -> 1 | H13: =IF(J13<>0,SUM(I14:I16)/J13,"-") -> -1.8 | I13: =IF(J13=0,0,H13*J13) -> -42.857143 | J13: ='9. Weighting'!N15 -> 23.809524 | K13: =IF(AND(D14="trifft nicht zu",D15="trifft nicht zu"),"trifft nicht zu","") | L13: =VLOOKUP(O13,$C$102:$E$106,3,FALSE()) -> 1 | M13: =VLOOKUP(D13,$C$102:$E$106,3,FALSE()) -> 1 | N13: =IF(L13=M13,"",'12.lan'!$D$240&VLOOKUP(L13,$C$102:$D$106,2,FALSE())&" ("&L13&")") | O13: =IF(K13="trifft nicht zu",C106,'9. Weighting'!N16) -> 1
B14: A2.1 | C14: ='12.lan'!D113 -> Fair business practices towards direct suppliers | D14: 1 | E14: =VLOOKUP(D14,$C$102:$D$106,2,FALSE()) -> medium | F14: ='12.lan'!$D$329 -> Introduce value between 0 and 10 | H14: 4 | I14: =IFERROR(J14*H14/10,0) -> 4.7619048 | J14: =IFERROR(J13*K14/(K15+K14),0) -> 11.904762 | K14: =VLOOKUP(D14,$C$102:$E$106,3,FALSE()) -> 1 | L14: =VLOOKUP(O14,$C$102:$E$106,3,FALSE()) -> 1 | M14: =VLOOKUP(D14,$C$102:$E$106,3,FALSE()) -> 1 | N14: =IF(L14=M14,"",'12.lan'!$D$240&VLOOKUP(L14,$C$102:$D$106,2,FALSE())&" ("&L14&")") | O14: =C104 -> 1
B15: A2.2 | C15: ='12.lan'!D114 -> Exercising a positive influence on solidarity and social justice in the supply chain | D15: =C104 -> 1 | E15: =VLOOKUP(D15,$C$102:$D$106,2,FALSE()) -> medium | F15: ='12.lan'!$D$329 -> Introduce value between 0 and 10 | I15: =IFERROR(J15*H15/10,0) -> 0 | J15: =IFERROR(J13*K15/(K14+K15),0) -> 11.904762 | K15: =VLOOKUP(D15,$C$102:$E$106,3,FALSE()) -> 1 | L15: =VLOOKUP(O15,$C$102:$E$106,3,FALSE()) -> 1 | M15: =VLOOKUP(D15,$C$102:$E$106,3,FALSE()) -> 1 | N15: =IF(L15=M15,"",'12.lan'!$D$240&VLOOKUP(L15,$C$102:$D$106,2,FALSE())&" ("&L15&")") | O15: =C104 -> 1
B16: A2.3 | C16: ='12.lan'!D115 -> Negative aspect: abuse of market power against suppliers | F16: ='12.lan'!$D$330 -> Introduce negative points between 0 and -200 | H16: -100 | I16: =H16*J13/50 -> -47.619048 | J16: =-200*J13/50 -> -95.238095
B17: A3 | C17: ='12.lan'!D116 -> Environmental sustainability in the supply chain | D17: =IF(K17="trifft nicht zu",C106,'9. Weighting'!O16) -> 1 | E17: =VLOOKUP(D17,$C$102:$D$106,2,FALSE()) -> medium | F17: =IF(K17="trifft nicht zu","trifft nicht zu",'9. Weighting'!O16) -> 1 | H17: =IF(J17<>0,SUM(I18:I19)/J17,"-") -> 0.1 | I17: =IF(J17=0,0,H17*J17) -> 2.3809524 | J17: ='9. Weighting'!O15 -> 23.809524 | K17: =IF(D18="trifft nicht zu","trifft nicht zu","") | L17: =VLOOKUP(O17,$C$102:$E$106,3,FALSE()) -> 1 | M17: =VLOOKUP(D17,$C$102:$E$106,3,FALSE()) -> 1 | N17: =IF(L17=M17,"",'12.lan'!$D$240&VLOOKUP(L17,$C$102:$D$106,2,FALSE())&" ("&L17&")") | O17: =IF(K17="trifft nicht zu",C106,'9. Weighting'!O16) -> 1
B18: A3.1 | C18: ='12.lan'!D117 -> Environmental impact throughout the supply chain | F18: ='12.lan'!$D$329 -> Introduce value between 0 and 10 | H18: 1 | I18: =J18*H18/10 -> 2.3809524 | J18: =J17*K18/K18 -> 23.809524 | K18: 1 | N18: =IF(L18=M18,"",'12.lan'!$D$240&VLOOKUP(L18,$C$102:$D$106,2,FALSE())&" ("&L18&")")
B19: A3.2 | C19: ='12.lan'!D118 -> Negative aspect: disproportionate environmental impact throughout the supply chain | F19: ='12.lan'!$D$330 -> Introduce negative points between 0 and -200 | I19: =H19*J17/50 -> 0 | J19: =-200*J17/50 -> -95.238095
B20: A4 | C20: ='12.lan'!D119 -> Transparency & co-determination in the supply chain | D20: =IF(K20="trifft nicht zu",C106,'9. Weighting'!P16) -> 1 | E20: =VLOOKUP(D20,$C$102:$D$106,2,FALSE()) -> medium | F20: =IF(K20="trifft nicht zu","trifft nicht zu",'9. Weighting'!P16) -> 1 | H20: =IF(J20<>0,SUM(I21:I22)/J20,"-") -> 0 | I20: =IF(J20=0,0,H20*J20) -> 0 | J20: ='9. Weighting'!P15 -> 23.809524 | K20: =IF(AND(D21="trifft nicht zu",D22="trifft nicht zu"),"trifft nicht zu","") | L20: =VLOOKUP(O20,$C$102:$E$106,3,FALSE()) -> 1 | M20: =VLOOKUP(D20,$C$102:$E$106,3,FALSE()) -> 1 | N20: =IF(L20=M20,"",'12.lan'!$D$240&VLOOKUP(L20,$C$102:$D$106,2,FALSE())&" ("&L20&")") | O20: =IF(K20="trifft nicht zu",C106,'9. Weighting'!P16) -> 1
B21: A4.1 | C21: ='12.lan'!D120 -> Transparency towards suppliers and their right to co-determination | D21: =C104 -> 1 | E21: =VLOOKUP(D21,$C$102:$D$106,2,FALSE()) -> medium | F21: ='12.lan'!$D$329 -> Introduce value between 0 and 10 | I21: =IFERROR(J21*H21/10,0) -> 0 | J21: =IFERROR(J20*K21/(K22+K21),0) -> 11.904762 | K21: =VLOOKUP(D21,$C$102:$E$106,3,FALSE()) -> 1 | L21: =VLOOKUP(O21,$C$102:$E$106,3,FALSE()) -> 1 | M21: =VLOOKUP(D21,$C$102:$E$106,3,FALSE()) -> 1 | N21: =IF(L21=M21,"",'12.lan'!$D$240&VLOOKUP(L21,$C$102:$D$106,2,FALSE())&" ("&L21&")") | O21: =C104 -> 1
B22: A4.2 | C22: ='12.lan'!D121 -> Positive influence on transparency and co-determination throughout the supply chain | D22: =C104 -> 1 | E22: =VLOOKUP(D22,$C$102:$D$106,2,FALSE()) -> medium | F22: ='12.lan'!$D$329 -> Introduce value between 0 and 10 | I22: =IFERROR(J22*H22/10,0) -> 0 | J22: =IFERROR(J20*K22/(K21+K22),0) -> 11.904762 | K22: =VLOOKUP(D22,$C$102:$E$106,3,FALSE()) -> 1 | L22: =VLOOKUP(O22,$C$102:$E$106,3,FALSE()) -> 1 | M22: =VLOOKUP(D22,$C$102:$E$106,3,FALSE()) -> 1 | N22: =IF(L22=M22,"",'12.lan'!$D$240&VLOOKUP(L22,$C$102:$D$106,2,FALSE())&" ("&L22&")") | O22: =C104 -> 1
B23: B | C23: ='12.lan'!D122 -> Owners, equity- and financial service providers | D23: =L23 -> 2 | E23: =VLOOKUP(D23,$C$102:$D$106,2,FALSE()) -> very high | H23: =IFERROR(I23/J23,0) -> 0.037037037 | I23: =I24+I28+I31+I35 -> 15.873016 | J23: =J24+J28+J31+J35 -> 428.57143 | L23: ='9. Weighting'!K50 -> 2 | N23: =IF(D23<>L23,'12.lan'!$D$240&VLOOKUP(L23,$C$102:$D$106,2,FALSE())&" ("&L23&")","")
B24: B1 | C24: ='12.lan'!D123 -> Ethical position in relation to financial resources | D24: =IF(K24="trifft nicht zu",C106,'9. Weighting'!M24) -> 1 | E24: =VLOOKUP(D24,$C$102:$D$106,2,FALSE()) -> medium | F24: =IF(K24="trifft nicht zu","trifft nicht zu",'9. Weighting'!M24) -> 1 | H24: =IF(J24<>0,SUM(I25:I27)/J24,"-") -> 0.16666667 | I24: =IF(J24=0,0,H24*J24) -> 15.873016 | J24: ='9. Weighting'!M23 -> 95.238095 | K24: =IF(AND(D25="trifft nicht zu",D26="trifft nicht zu",,D27="trifft nicht zu"),"trifft nicht zu","") | L24: =VLOOKUP(O24,$C$102:$E$106,3,FALSE()) -> 1 | M24: =VLOOKUP(D24,$C$102:$E$106,3,FALSE()) -> 1 | N24: =IF(L24=M24,"",'12.lan'!$D$240&VLOOKUP(L24,$C$102:$D$106,2,FALSE())&" ("&L24&")") | O24: =IF(K24="trifft nicht zu",C106,'9. Weighting'!M24) -> 1
B25: B1.1 | C25: ='12.lan'!D124 -> Financial independence through equity financing | D25: =C104 -> 1 | E25: =VLOOKUP(D25,$C$102:$D$106,2,FALSE()) -> medium | F25: ='12.lan'!$D$329 -> Introduce value between 0 and 10 | H25: 0 | I25: =IFERROR(J25*H25/10,0) -> 0 | J25: =IFERROR($J$24*K25/($K$27+$K$26+$K$25),0) -> 31.746032 | K25: =VLOOKUP(D25,$C$102:$E$106,3,FALSE()) -> 1 | L25: =VLOOKUP(O25,$C$102:$E$106,3,FALSE()) -> 1 | M25: =VLOOKUP(D25,$C$102:$E$106,3,FALSE()) -> 1 | N25: =IF(L25=M25,"",'12.lan'!$D$240&VLOOKUP(L25,$C$102:$D$106,2,FALSE())&" ("&L25&")") | O25: =C104 -> 1
B26: B1.2 | C26: ='12.lan'!D125 -> Common Good-orientated borrowing | D26: =C104 -> 1 | E26: =VLOOKUP(D26,$C$102:$D$106,2,FALSE()) -> medium | F26: ='12.lan'!$D$329 -> Introduce value between 0 and 10 | H26: 5 | I26: =IFERROR(J26*H26/10,0) -> 15.873016 | J26: =IFERROR($J$24*K26/($K$27+$K$26+$K$25),0) -> 31.746032 | K26: =VLOOKUP(D26,$C$102:$E$106,3,FALSE()) -> 1 | L26: =VLOOKUP(O26,$C$102:$E$106,3,FALSE()) -> 1 | M26: =VLOOKUP(D26,$C$102:$E$106,3,FALSE()) -> 1 | N26: =IF(L26=M26,"",'12.lan'!$D$240&VLOOKUP(L26,$C$102:$D$106,2,FALSE())&" ("&L26&")") | O26: =C104 -> 1
B27: B1.3 | C27: ='12.lan'!D126 -> Ethical position of external financial partners | D27: =C104 -> 1 | E27: =VLOOKUP(D27,$C$102:$D$106,2,FALSE()) -> medium | F27: ='12.lan'!$D$329 -> Introduce value between 0 and 10 | H27: 0 | I27: =IFERROR(J27*H27/10,0) -> 0 | J27: =IFERROR($J$24*K27/($K$27+$K$26+$K$25),0) -> 31.746032 | K27: =VLOOKUP(D27,$C$102:$E$106,3,FALSE()) -> 1 | L27: =VLOOKUP(O27,$C$102:$E$106,3,FALSE()) -> 1 | M27: =VLOOKUP(D27,$C$102:$E$106,3,FALSE()) -> 1 | N27: =IF(L27=M27,"",'12.lan'!$D$240&VLOOKUP(L27,$C$102:$D$106,2,FALSE())&" ("&L27&")") | O27: =C104 -> 1
B28: B2 | C28: ='12.lan'!D127 -> Social position in relation to financial resources | D28: =IF(K28="trifft nicht zu",C106,'9. Weighting'!N24) -> 1.5 | E28: =VLOOKUP(D28,$C$102:$D$106,2,FALSE()) -> high | F28: =IF(K28="trifft nicht zu","trifft nicht zu",'9. Weighting'!N24) -> 1.5 | H28: =IF(J28<>0,SUM(I29:I30)/J28,"-") -> 0 | I28: =IF(J28=0,0,H28*J28) -> 0 | J28: ='9. Weighting'!N23 -> 142.85714 | L28: =VLOOKUP(O28,$C$102:$E$106,3,FALSE()) -> 1.5 | M28: =VLOOKUP(D28,$C$102:$E$106,3,FALSE()) -> 1.5 | N28: =IF(L28=M28,"",'12.lan'!$D$240&VLOOKUP(L28,$C$102:$D$106,2,FALSE())&" ("&L28&")") | O28: =IF(K28="trifft nicht zu",C106,'9. Weighting'!N24) -> 1.5
B29: B2.1 | C29: ='12.lan'!D128 -> Solidarity and Common Good-orientated use of funds | F29: ='12.lan'!$D$329 -> Introduce value between 0 and 10 | I29: =J29*H29/10 -> 0 | J29: =$J$28*K29/(K29) -> 142.85714 | K29: 1 | L29: =VLOOKUP(O29,$C$102:$E$106,3,FALSE()) -> #N/A | M29: =VLOOKUP(D29,$C$102:$E$106,3,FALSE()) -> #N/A
B30: B2.2 | C30: ='12.lan'!D129 -> Negative aspect: unfair distribution of funds | F30: ='12.lan'!$D$330 -> Introduce negative points between 0 and -200 | I30: =H30*J28/50 -> 0 | J30: =-200*J28/50 -> -571.42857
B31: B3 | C31: ='12.lan'!D130 -> Use of funds in relation to social and environmental impacts | D31: =IF(K31="trifft nicht zu",C106,'9. Weighting'!O24) -> 1.5 | E31: =VLOOKUP(D31,$C$102:$D$106,2,FALSE()) -> high | F31: =IF(K31="trifft nicht zu","trifft nicht zu",'9. Weighting'!O24) -> 1.5 | H31: =IF(J31<>0,SUM(I32:I34)/J31,"-") -> 0 | I31: =IF(J31=0,0,H31*J31) -> 0 | J31: ='9. Weighting'!O23 -> 142.85714 | K31: =IF(AND(D32="trifft nicht zu",D33="trifft nicht zu"),"trifft nicht zu","") | L31: =VLOOKUP(O31,$C$102:$E$106,3,FALSE()) -> 1.5 | M31: =VLOOKUP(D31,$C$102:$E$106,3,FALSE()) -> 1.5 | N31: =IF(L31=M31,"",'12.lan'!$D$240&VLOOKUP(L31,$C$102:$D$106,2,FALSE())&" ("&L31&")") | O31: =IF(K31="trifft nicht zu",C106,'9. Weighting'!O24) -> 1.5
B32: B3.1 | C32: ='12.lan'!D131 -> Environmental quality of investments | D32: =C104 -> 1 | E32: =VLOOKUP(D32,$C$102:$D$106,2,FALSE()) -> medium | F32: ='12.lan'!$D$329 -> Introduce value between 0 and 10 | H32: 0 | I32: =IFERROR(J32*H32/10,0) -> 0 | J32: =IFERROR($J$31*K32/($K$32+$K$33),0) -> 71.428571 | K32: =VLOOKUP(D32,$C$102:$E$106,3,FALSE()) -> 1 | L32: =VLOOKUP(O32,$C$102:$E$106,3,FALSE()) -> 1 | M32: =VLOOKUP(D32,$C$102:$E$106,3,FALSE()) -> 1 | N32: =IF(L32=M32,"",'12.lan'!$D$240&VLOOKUP(L32,$C$102:$D$106,2,FALSE())&" ("&L32&")") | O32: =C104 -> 1
B33: B3.2 | C33: ='12.lan'!D132 -> Common Good-orientated investment | D33: =C104 -> 1 | E33: =VLOOKUP(D33,$C$102:$D$106,2,FALSE()) -> medium | F33: ='12.lan'!$D$329 -> Introduce value between 0 and 10 | H33: 0 | I33: =IFERROR(J33*H33/10,0) -> 0 | J33: =IFERROR($J$31*K33/($K$32+$K$33),0) -> 71.428571 | K33: =VLOOKUP(D33,$C$102:$E$106,3,FALSE()) -> 1 | L33: =VLOOKUP(O33,$C$102:$E$106,3,FALSE()) -> 1 | M33: =VLOOKUP(D33,$C$102:$E$106,3,FALSE()) -> 1 | N33: =IF(L33=M33,"",'12.lan'!$D$240&VLOOKUP(L33,$C$102:$D$106,2,FALSE())&" ("&L33&")") | O33: =C104 -> 1
B34: B3.3 | C34: ='12.lan'!D133 -> Negative aspect: reliance on environmentally unsafe resources | F34: ='12.lan'!$D$330 -> Introduce negative points between 0 and -200 | H34: 0 | I34: =H34*J31/50 -> 0 | J34: =-200*J31/50 -> -571.42857
B35: B4 | C35: ='12.lan'!D134 -> Ownership and co-determination | D35: =IF(K35="trifft nicht zu",C106,'9. Weighting'!P24) -> 0.5 | E35: =VLOOKUP(D35,$C$102:$D$106,2,FALSE()) -> low | F35: =IF(K35="trifft nicht zu","trifft nicht zu",'9. Weighting'!P24) -> 0.5 | H35: =IF(J35<>0,SUM(I36:I37)/J35,"-") -> 0 | I35: =IF(J35=0,0,H35*J35) -> 0 | J35: ='9. Weighting'!P23 -> 47.619048 | L35: =VLOOKUP(O35,$C$102:$E$106,3,FALSE()) -> 0.5 | M35: =VLOOKUP(D35,$C$102:$E$106,3,FALSE()) -> 0.5 | N35: =IF(L35=M35,"",'12.lan'!$D$240&VLOOKUP(L35,$C$102:$D$106,2,FALSE())&" ("&L35&")") | O35: =IF(K35="trifft nicht zu",C106,'9. Weighting'!P24) -> 0.5
B36: B4.1 | C36: ='12.lan'!D135 -> Common Good-orientated ownership structure | F36: ='12.lan'!$D$329 -> Introduce value between 0 and 10 | I36: =J36*H36/10 -> 0 | J36: =$J$35*K36/(K36) -> 47.619048 | K36: 1
B37: B4.2 | C37: ='12.lan'!D136 -> Negative aspect: hostile takeover | F37: ='12.lan'!$D$330 -> Introduce negative points between 0 and -200 | I37: =H37*J35/50 -> 0 | J37: =-200*J35/50 -> -190.47619
B38: C | C38: ='12.lan'!D137 -> Employees | D38: =L38 -> 0.5 | E38: =VLOOKUP(D38,$C$102:$D$106,2,FALSE()) -> low | H38: =IFERROR(I38/J38,0) -> -0.10916667 | I38: =I39+I44+I49+I54 -> -10.396825 | J38: =J39+J44+J49+J54 -> 95.238095 | L38: ='9. Weighting'!K51 -> 0.5 | N38: =IF(D38<>L38,'12.lan'!$D$240&VLOOKUP(L38,$C$102:$D$106,2,FALSE())&" ("&L38&")","")
B39: C1 | C39: ='12.lan'!D138 -> Human dignity in the workplace and working environment | D39: =IF(K39="trifft nicht zu",C101,'9. Weighting'!M30) -> 1 | E39: =VLOOKUP(D39,$C$102:$D$106,2,FALSE()) -> medium | F39: =IF(K39="trifft nicht zu","trifft nicht zu",'9. Weighting'!M30) -> 1 | H39: =IF(J39<>0,SUM(I40:I43)/J39,"-") -> 0.033333333 | I39: =IF(J39=0,0,H39*J39) -> 0.79365079 | J39: ='9. Weighting'!M29 -> 23.809524 | K39: =IF(AND(D40="trifft nicht zu",D41="trifft nicht zu",,D42="trifft nicht zu"),"trifft nicht zu","") | L39: =VLOOKUP(O39,$C$102:$E$106,3,FALSE()) -> 1 | M39: =VLOOKUP(D39,$C$102:$E$106,3,FALSE()) -> 1 | N39: =IF(L39=M39,"",'12.lan'!$D$240&VLOOKUP(L39,$C$102:$D$106,2,FALSE())&" ("&L39&")") | O39: =IF(K39="trifft nicht zu",C106,'9. Weighting'!M30) -> 1
B40: C1.1 | C40: ='12.lan'!D139 -> Employee-focused organisational culture | D40: =C104 -> 1 | E40: =VLOOKUP(D40,$C$102:$D$106,2,FALSE()) -> medium | F40: ='12.lan'!$D$329 -> Introduce value between 0 and 10 | H40: 1 | I40: =IFERROR(J40*H40/10,0) -> 0.79365079 | J40: =IFERROR($J$39*K40/(SUM($K$40:$K$42)),0) -> 7.9365079 | K40: =VLOOKUP(D40,$C$102:$E$106,3,FALSE()) -> 1 | L40: =VLOOKUP(O40,$C$102:$E$106,3,FALSE()) -> 1 | M40: =VLOOKUP(D40,$C$102:$E$106,3,FALSE()) -> 1 | N40: =IF(L40=M40,"",'12.lan'!$D$240&VLOOKUP(L40,$C$102:$D$106,2,FALSE())&" ("&L40&")") | O40: =C104 -> 1
B41: C1.2 | C41: ='12.lan'!D140 -> Health promotion and occupational health and safety | D41: =C104 -> 1 | E41: =VLOOKUP(D41,$C$102:$D$106,2,FALSE()) -> medium | F41: ='12.lan'!$D$329 -> Introduce value between 0 and 10 | I41: =IFERROR(J41*H41/10,0) -> 0 | J41: =IFERROR($J$39*K41/(SUM($K$40:$K$42)),0) -> 7.9365079 | K41: =VLOOKUP(D41,$C$102:$E$106,3,FALSE()) -> 1 | L41: =VLOOKUP(O41,$C$102:$E$106,3,FALSE()) -> 1 | M41: =VLOOKUP(D41,$C$102:$E$106,3,FALSE()) -> 1 | N41: =IF(L41=M41,"",'12.lan'!$D$240&VLOOKUP(L41,$C$102:$D$106,2,FALSE())&" ("&L41&")") | O41: =C104 -> 1
B42: C1.3 | C42: ='12.lan'!D141 -> Diversity and equal opportunities | D42: =C104 -> 1 | E42: =VLOOKUP(D42,$C$102:$D$106,2,FALSE()) -> medium | F42: ='12.lan'!$D$329 -> Introduce value between 0 and 10 | I42: =IFERROR(J42*H42/10,0) -> 0 | J42: =IFERROR($J$39*K42/(SUM($K$40:$K$42)),0) -> 7.9365079 | K42: =VLOOKUP(D42,$C$102:$E$106,3,FALSE()) -> 1 | L42: =VLOOKUP(O42,$C$102:$E$106,3,FALSE()) -> 1 | M42: =VLOOKUP(D42,$C$102:$E$106,3,FALSE()) -> 1 | N42: =IF(L42=M42,"",'12.lan'!$D$240&VLOOKUP(L42,$C$102:$D$106,2,FALSE())&" ("&L42&")") | O42: =C104 -> 1
B43: C1.4 | C43: ='12.lan'!D142 -> Negative aspect: unfit working conditions | F43: ='12.lan'!$D$330 -> Introduce negative points between 0 and -200 | H43: 0 | I43: =H43*J39/50 -> 0 | J43: =-200*J39/50 -> -95.238095
B44: C2 | C44: ='12.lan'!D143 -> Self-determined working arrangements | D44: =IF(K44="trifft nicht zu",C106,'9. Weighting'!N30) -> 1 | E44: =VLOOKUP(D44,$C$102:$D$106,2,FALSE()) -> medium | F44: =IF(K44="trifft nicht zu","trifft nicht zu",'9. Weighting'!N30) -> 1 | H44: =IF(J44<>0,SUM(I45:I48)/J44,"-") -> -0.02 | I44: =IF(J44=0,0,H44*J44) -> -0.47619048 | J44: ='9. Weighting'!N29 -> 23.809524 | K44: =IF(AND(D45="trifft nicht zu",D46="trifft nicht zu",,D47="trifft nicht zu"),"trifft nicht zu","") | L44: =VLOOKUP(O44,$C$102:$E$106,3,FALSE()) -> 1 | M44: =VLOOKUP(D44,$C$102:$E$106,3,FALSE()) -> 1 | N44: =IF(L44=M44,"",'12.lan'!$D$240&VLOOKUP(L44,$C$102:$D$106,2,FALSE())&" ("&L44&")") | O44: =IF(K44="trifft nicht zu",C106,'9. Weighting'!N30) -> 1
B45: C2.1 | C45: ='12.lan'!D144 -> Pay structure | D45: =C104 -> 1 | E45: =VLOOKUP(D45,$C$102:$D$106,2,FALSE()) -> medium | F45: ='12.lan'!$D$329 -> Introduce value between 0 and 10 | I45: =IFERROR(J45*H45/10,0) -> 0 | J45: =IFERROR($J$44*K45/(SUM($K$45:$K$47)),0) -> 7.9365079 | K45: =VLOOKUP(D45,$C$102:$E$106,3,FALSE()) -> 1 | L45: =VLOOKUP(O45,$C$102:$E$106,3,FALSE()) -> 1 | M45: =VLOOKUP(D45,$C$102:$E$106,3,FALSE()) -> 1 | N45: =IF(L45=M45,"",'12.lan'!$D$240&VLOOKUP(L45,$C$102:$D$106,2,FALSE())&" ("&L45&")") | O45: =C104 -> 1
B46: C2.2 | C46: ='12.lan'!D145 -> Structuring working time | D46: =C104 -> 1 | E46: =VLOOKUP(D46,$C$102:$D$106,2,FALSE()) -> medium | F46: ='12.lan'!$D$329 -> Introduce value between 0 and 10 | I46: =IFERROR(J46*H46/10,0) -> 0 | J46: =IFERROR($J$44*K46/(SUM($K$45:$K$47)),0) -> 7.9365079 | K46: =VLOOKUP(D46,$C$102:$E$106,3,FALSE()) -> 1 | L46: =VLOOKUP(O46,$C$102:$E$106,3,FALSE()) -> 1 | M46: =VLOOKUP(D46,$C$102:$E$106,3,FALSE()) -> 1 | N46: =IF(L46=M46,"",'12.lan'!$D$240&VLOOKUP(L46,$C$102:$D$106,2,FALSE())&" ("&L46&")") | O46: =C104 -> 1
B47: C2.3 | C47: ='12.lan'!D146 -> Employment structure and work-life balance | D47: =C104 -> 1 | E47: =VLOOKUP(D47,$C$102:$D$106,2,FALSE()) -> medium | F47: ='12.lan'!$D$329 -> Introduce value between 0 and 10 | I47: =IFERROR(J47*H47/10,0) -> 0 | J47: =IFERROR($J$44*K47/(SUM($K$45:$K$47)),0) -> 7.9365079 | K47: =VLOOKUP(D47,$C$102:$E$106,3,FALSE()) -> 1 | L47: =VLOOKUP(O47,$C$102:$E$106,3,FALSE()) -> 1 | M47: =VLOOKUP(D47,$C$102:$E$106,3,FALSE()) -> 1 | N47: =IF(L47=M47,"",'12.lan'!$D$240&VLOOKUP(L47,$C$102:$D$106,2,FALSE())&" ("&L47&")") | O47: =C104 -> 1
B48: C2.4 | C48: ='12.lan'!D147 -> Negative aspect: unfair employment contracts | F48: ='12.lan'!$D$330 -> Introduce negative points between 0 and -200 | H48: -1 | I48: =H48*J44/50 -> -0.47619048 | J48: =-200*J44/50 -> -95.238095
B49: C3 | C49: ='12.lan'!D148 -> Environmentally-friendly behaviour of staff | D49: =IF(K49="trifft nicht zu",C101,'9. Weighting'!O30) -> 1.5 | E49: =VLOOKUP(D49,$C$102:$D$106,2,FALSE()) -> high | F49: =IF(K49="trifft nicht zu","trifft nicht zu",'9. Weighting'!O30) -> 1.5 | H49: =IF(J49<>0,SUM(I50:I53)/J49,"-") -> -0.3 | I49: =IF(J49=0,0,H49*J49) -> -10.714286 | J49: ='9. Weighting'!O29 -> 35.714286 | K49: =IF(AND(D50="trifft nicht zu",D51="trifft nicht zu",,D52="trifft nicht zu"),"trifft nicht zu","") | L49: =VLOOKUP(O49,$C$102:$E$106,3,FALSE()) -> 1.5 | M49: =VLOOKUP(D49,$C$102:$E$106,3,FALSE()) -> 1.5 | N49: =IF(L49=M49,"",'12.lan'!$D$240&VLOOKUP(L49,$C$102:$D$106,2,FALSE())&" ("&L49&")") | O49: =IF(K49="trifft nicht zu",C106,'9. Weighting'!O30) -> 1.5
B50: C3.1 | C50: ='12.lan'!D149 -> Food during working hours | D50: =C104 -> 1 | E50: =VLOOKUP(D50,$C$102:$D$106,2,FALSE()) -> medium | F50: ='12.lan'!$D$329 -> Introduce value between 0 and 10 | H50: 0 | I50: =IFERROR(J50*H50/10,0) -> 0 | J50: =IFERROR($J$49*K50/(SUM($K$50:$K$52)),0) -> 11.904762 | K50: =VLOOKUP(D50,$C$102:$E$106,3,FALSE()) -> 1 | L50: =VLOOKUP(O50,$C$102:$E$106,3,FALSE()) -> 1 | M50: =VLOOKUP(D50,$C$102:$E$106,3,FALSE()) -> 1 | N50: =IF(L50=M50,"",'12.lan'!$D$240&VLOOKUP(L50,$C$102:$D$106,2,FALSE())&" ("&L50&")") | O50: =C104 -> 1
B51: C3.2 | C51: ='12.lan'!D150 -> Travel to work | D51: =C104 -> 1 | E51: =VLOOKUP(D51,$C$102:$D$106,2,FALSE()) -> medium | F51: ='12.lan'!$D$329 -> Introduce value between 0 and 10 | I51: =IFERROR(J51*H51/10,0) -> 0 | J51: =IFERROR($J$49*K51/(SUM($K$50:$K$52)),0) -> 11.904762 | K51: =VLOOKUP(D51,$C$102:$E$106,3,FALSE()) -> 1 | L51: =VLOOKUP(O51,$C$102:$E$106,3,FALSE()) -> 1 | M51: =VLOOKUP(D51,$C$102:$E$106,3,FALSE()) -> 1 | N51: =IF(L51=M51,"",'12.lan'!$D$240&VLOOKUP(L51,$C$102:$D$106,2,FALSE())&" ("&L51&")") | O51: =C104 -> 1
B52: C3.3 | C52: ='12.lan'!D151 -> Organisational culture, cultivating awareness for an environmentally-friendly approach | D52: =C104 -> 1 | E52: =VLOOKUP(D52,$C$102:$D$106,2,FALSE()) -> medium | F52: ='12.lan'!$D$329 -> Introduce value between 0 and 10 | H52: 3 | I52: =IFERROR(J52*H52/10,0) -> 3.5714286 | J52: =IFERROR($J$49*K52/(SUM($K$50:$K$52)),0) -> 11.904762 | K52: =VLOOKUP(D52,$C$102:$E$106,3,FALSE()) -> 1 | L52: =VLOOKUP(O52,$C$102:$E$106,3,FALSE()) -> 1 | M52: =VLOOKUP(D52,$C$102:$E$106,3,FALSE()) -> 1 | N52: =IF(L52=M52,"",'12.lan'!$D$240&VLOOKUP(L52,$C$102:$D$106,2,FALSE())&" ("&L52&")") | O52: =C104 -> 1
B53: C3.4 | C53: ='12.lan'!D152 -> Negative aspect: guidance on waste/ environmentally damaging practices | F53: ='12.lan'!$D$330 -> Introduce negative points between 0 and -200 | H53: -20 | I53: =H53*J49/50 -> -14.285714 | J53: =-200*J49/50 -> -142.85714
B54: C4 | C54: ='12.lan'!D153 -> Co-determination and transparency within the organisation | D54: =IF(K54="trifft nicht zu",C106,'9. Weighting'!P30) -> 0.5 | E54: =VLOOKUP(D54,$C$102:$D$106,2,FALSE()) -> low | F54: =IF(K54="trifft nicht zu","trifft nicht zu",'9. Weighting'!P30) -> 0.5 | H54: =IF(J54<>0,SUM(I55:I58)/J54,"-") -> 0 | I54: =IF(J54=0,0,H54*J54) -> 0 | J54: ='9. Weighting'!P29 -> 11.904762 | K54: =IF(AND(D55="trifft nicht zu",D56="trifft nicht zu",,D57="trifft nicht zu"),"trifft nicht zu","") | L54: =VLOOKUP(O54,$C$102:$E$106,3,FALSE()) -> 0.5 | M54: =VLOOKUP(D54,$C$102:$E$106,3,FALSE()) -> 0.5 | N54: =IF(L54=M54,"",'12.lan'!$D$240&VLOOKUP(L54,$C$102:$D$106,2,FALSE())&" ("&L54&")") | O54: =IF(K54="trifft nicht zu",C106,'9. Weighting'!P30) -> 0.5
B55: C4.1 | C55: ='12.lan'!D154 -> Transparency within the organisation | D55: =C104 -> 1 | E55: =VLOOKUP(D55,$C$102:$D$106,2,FALSE()) -> medium | F55: ='12.lan'!$D$329 -> Introduce value between 0 and 10 | I55: =IFERROR(J55*H55/10,0) -> 0 | J55: =IFERROR($J$54*K55/(SUM($K$55:$K$57)),0) -> 3.968254 | K55: =VLOOKUP(D55,$C$102:$E$106,3,FALSE()) -> 1 | L55: =VLOOKUP(O55,$C$102:$E$106,3,FALSE()) -> 1 | M55: =VLOOKUP(D55,$C$102:$E$106,3,FALSE()) -> 1 | N55: =IF(L55=M55,"",'12.lan'!$D$240&VLOOKUP(L55,$C$102:$D$106,2,FALSE())&" ("&L55&")") | O55: =C104 -> 1
B56: C4.2 | C56: ='12.lan'!D155 -> Legitimation of the management | D56: =C104 -> 1 | E56: =VLOOKUP(D56,$C$102:$D$106,2,FALSE()) -> medium | F56: ='12.lan'!$D$329 -> Introduce value between 0 and 10 | I56: =IFERROR(J56*H56/10,0) -> 0 | J56: =IFERROR($J$54*K56/(SUM($K$55:$K$57)),0) -> 3.968254 | K56: =VLOOKUP(D56,$C$102:$E$106,3,FALSE()) -> 1 | L56: =VLOOKUP(O56,$C$102:$E$106,3,FALSE()) -> 1 | M56: =VLOOKUP(D56,$C$102:$E$106,3,FALSE()) -> 1 | N56: =IF(L56=M56,"",'12.lan'!$D$240&VLOOKUP(L56,$C$102:$D$106,2,FALSE())&" ("&L56&")") | O56: =C104 -> 1
B57: C4.3 | C57: ='12.lan'!D156 -> Employee co-determination | D57: =C104 -> 1 | E57: =VLOOKUP(D57,$C$102:$D$106,2,FALSE()) -> medium | F57: ='12.lan'!$D$329 -> Introduce value between 0 and 10 | I57: =IFERROR(J57*H57/10,0) -> 0 | J57: =IFERROR($J$54*K57/(SUM($K$55:$K$57)),0) -> 3.968254 | K57: =VLOOKUP(D57,$C$102:$E$106,3,FALSE()) -> 1 | L57: =VLOOKUP(O57,$C$102:$E$106,3,FALSE()) -> 1 | M57: =VLOOKUP(D57,$C$102:$E$106,3,FALSE()) -> 1 | N57: =IF(L57=M57,"",'12.lan'!$D$240&VLOOKUP(L57,$C$102:$D$106,2,FALSE())&" ("&L57&")") | O57: =C104 -> 1
B58: C4.4 | C58: ='12.lan'!D157 -> Negative aspect: obstruction of works councils | F58: ='12.lan'!$D$330 -> Introduce negative points between 0 and -200 | I58: =H58*J54/50 -> 0 | J58: =-200*J54/50 -> -47.619048
B59: D | C59: ='12.lan'!D158 -> Customers and other companies | D59: =L59 -> 1 | E59: =VLOOKUP(D59,$C$102:$D$106,2,FALSE()) -> medium | H59: =IFERROR(I59/J59,0) -> -1.125 | I59: =I60+I64+I68+I72 -> -214.28571 | J59: =J60+J64+J68+J72 -> 190.47619 | L59: ='9. Weighting'!K52 -> 1 | N59: =IF(D59<>L59,'12.lan'!$D$240&VLOOKUP(L59,$C$102:$D$106,2,FALSE())&" ("&L59&")","")
B60: D1 | C60: ='12.lan'!D159 -> Ethical customer relations | D60: =IF(K60="trifft nicht zu",C106,'9. Weighting'!M37) -> 1 | E60: =VLOOKUP(D60,$C$102:$D$106,2,FALSE()) -> medium | F60: =IF(K60="trifft nicht zu","trifft nicht zu",'9. Weighting'!M37) -> 1 | H60: =IF(J60<>0,SUM(I61:I63)/J60,"-") -> -3.4 | I60: =IF(J60=0,0,H60*J60) -> -161.90476 | J60: ='9. Weighting'!M36 -> 47.619048 | K60: =IF(AND(D61="trifft nicht zu",D62="trifft nicht zu"),"trifft nicht zu","") | L60: =VLOOKUP(O60,$C$102:$E$106,3,FALSE()) -> 1 | M60: =VLOOKUP(D60,$C$102:$E$106,3,FALSE()) -> 1 | N60: =IF(L60=M60,"",'12.lan'!$D$240&VLOOKUP(L60,$C$102:$D$106,2,FALSE())&" ("&L60&")") | O60: =IF(K60="trifft nicht zu",C106,'9. Weighting'!M37) -> 1
B61: D1.1 | C61: ='12.lan'!D160 -> Respect for human dignity in communication with customers | D61: =C104 -> 1 | E61: =VLOOKUP(D61,$C$102:$D$106,2,FALSE()) -> medium | F61: ='12.lan'!$D$329 -> Introduce value between 0 and 10 | H61: 6 | I61: =IFERROR(J61*H61/10,0) -> 14.285714 | J61: =IFERROR($J$60*K61/(SUM($K$61:$K$62)),0) -> 23.809524 | K61: =VLOOKUP(D61,$C$102:$E$106,3,FALSE()) -> 1 | L61: =VLOOKUP(O61,$C$102:$E$106,3,FALSE()) -> 1 | M61: =VLOOKUP(D61,$C$102:$E$106,3,FALSE()) -> 1 | N61: =IF(L61=M61,"",'12.lan'!$D$240&VLOOKUP(L61,$C$102:$D$106,2,FALSE())&" ("&L61&")") | O61: =C104 -> 1
B62: D1.2 | C62: ='12.lan'!D161 -> Barrier-free access | D62: =C104 -> 1 | E62: =VLOOKUP(D62,$C$102:$D$106,2,FALSE()) -> medium | F62: ='12.lan'!$D$329 -> Introduce value between 0 and 10 | H62: 6 | I62: =IFERROR(J62*H62/10,0) -> 14.285714 | J62: =IFERROR($J$60*K62/(SUM($K$61:$K$62)),0) -> 23.809524 | K62: =VLOOKUP(D62,$C$102:$E$106,3,FALSE()) -> 1 | L62: =VLOOKUP(O62,$C$102:$E$106,3,FALSE()) -> 1 | M62: =VLOOKUP(D62,$C$102:$E$106,3,FALSE()) -> 1 | N62: =IF(L62=M62,"",'12.lan'!$D$240&VLOOKUP(L62,$C$102:$D$106,2,FALSE())&" ("&L62&")") | O62: =C104 -> 1
B63: D1.3 | C63: ='12.lan'!D162 -> Negative aspect: unethical advertising | F63: ='12.lan'!$D$330 -> Introduce negative points between 0 and -200 | H63: -200 | I63: =H63*J60/50 -> -190.47619 | J63: =-200*J60/50 -> -190.47619
B64: D2 | C64: ='12.lan'!D163 -> Cooperation and solidarity with other companies | D64: =IF(K64="trifft nicht zu",C106,'9. Weighting'!N37) -> 1 | E64: =VLOOKUP(D64,$C$102:$D$106,2,FALSE()) -> medium | F64: =IF(K64="trifft nicht zu","trifft nicht zu",'9. Weighting'!N37) -> 1 | H64: =IF(J64<>0,SUM(I65:I67)/J64,"-") -> 0 | I64: =IF(J64=0,0,H64*J64) -> 0 | J64: ='9. Weighting'!N36 -> 47.619048 | K64: =IF(AND(D65="trifft nicht zu",D66="trifft nicht zu"),"trifft nicht zu","") | L64: =VLOOKUP(O64,$C$102:$E$106,3,FALSE()) -> 1 | M64: =VLOOKUP(D64,$C$102:$E$106,3,FALSE()) -> 1 | N64: =IF(L64=M64,"",'12.lan'!$D$240&VLOOKUP(L64,$C$102:$D$106,2,FALSE())&" ("&L64&")") | O64: =IF(K64="trifft nicht zu",C106,'9. Weighting'!N37) -> 1
B65: D2.1 | C65: ='12.lan'!D164 -> Cooperation with other companies | D65: =C104 -> 1 | E65: =VLOOKUP(D65,$C$102:$D$106,2,FALSE()) -> medium | F65: ='12.lan'!$D$329 -> Introduce value between 0 and 10 | I65: =IFERROR(J65*H65/10,0) -> 0 | J65: =IFERROR($J$64*K65/(SUM($K$65:$K$66)),0) -> 23.809524 | K65: =VLOOKUP(D65,$C$102:$E$106,3,FALSE()) -> 1 | L65: =VLOOKUP(O65,$C$102:$E$106,3,FALSE()) -> 1 | M65: =VLOOKUP(D65,$C$102:$E$106,3,FALSE()) -> 1 | N65: =IF(L65=M65,"",'12.lan'!$D$240&VLOOKUP(L65,$C$102:$D$106,2,FALSE())&" ("&L65&")") | O65: =C104 -> 1
B66: D2.2 | C66: ='12.lan'!D165 -> Solidarity with other companies | D66: =C104 -> 1 | E66: =VLOOKUP(D66,$C$102:$D$106,2,FALSE()) -> medium | F66: ='12.lan'!$D$329 -> Introduce value between 0 and 10 | I66: =IFERROR(J66*H66/10,0) -> 0 | J66: =IFERROR($J$64*K66/(SUM($K$65:$K$66)),0) -> 23.809524 | K66: =VLOOKUP(D66,$C$102:$E$106,3,FALSE()) -> 1 | L66: =VLOOKUP(O66,$C$102:$E$106,3,FALSE()) -> 1 | M66: =VLOOKUP(D66,$C$102:$E$106,3,FALSE()) -> 1 | N66: =IF(L66=M66,"",'12.lan'!$D$240&VLOOKUP(L66,$C$102:$D$106,2,FALSE())&" ("&L66&")") | O66: =C104 -> 1
B67: D2.3 | C67: ='12.lan'!D166 -> Negative aspect: abuse of market power to the detriment of other companies | F67: ='12.lan'!$D$330 -> Introduce negative points between 0 and -200 | I67: =H67*J64/50 -> 0 | J67: =-200*J64/50 -> -190.47619
B68: D3 | C68: ='12.lan'!D167 -> Impact on the environment of the use and disposal of products and services | D68: =IF(K68="trifft nicht zu",C106,'9. Weighting'!O37) -> 1 | E68: =VLOOKUP(D68,$C$102:$D$106,2,FALSE()) -> medium | F68: =IF(K68="trifft nicht zu","trifft nicht zu",'9. Weighting'!O37) -> 1 | H68: =IF(J68<>0,SUM(I69:I71)/J68,"-") -> 0 | I68: =IF(J68=0,0,H68*J68) -> 0 | J68: ='9. Weighting'!O36 -> 47.619048 | K68: =IF(AND(D69="trifft nicht zu",D70="trifft nicht zu"),"trifft nicht zu","") | L68: =VLOOKUP(O68,$C$102:$E$106,3,FALSE()) -> 1 | M68: =VLOOKUP(D68,$C$102:$E$106,3,FALSE()) -> 1 | N68: =IF(L68=M68,"",'12.lan'!$D$240&VLOOKUP(L68,$C$102:$D$106,2,FALSE())&" ("&L68&")") | O68: =IF(K68="trifft nicht zu",C106,'9. Weighting'!O37) -> 1
B69: D3.1 | C69: ='12.lan'!D168 -> Environmental cost-benefit ration of products and services (efficiency and consistency) | D69: =C104 -> 1 | E69: =VLOOKUP(D69,$C$102:$D$106,2,FALSE()) -> medium | F69: ='12.lan'!$D$329 -> Introduce value between 0 and 10 | I69: =IFERROR(J69*H69/10,0) -> 0 | J69: =IFERROR($J$68*K69/(SUM($K$69:$K$70)),0) -> 23.809524 | K69: =VLOOKUP(D69,$C$102:$E$106,3,FALSE()) -> 1 | L69: =VLOOKUP(O69,$C$102:$E$106,3,FALSE()) -> 1 | M69: =VLOOKUP(D69,$C$102:$E$106,3,FALSE()) -> 1 | N69: =IF(L69=M69,"",'12.lan'!$D$240&VLOOKUP(L69,$C$102:$D$106,2,FALSE())&" ("&L69&")") | O69: =C104 -> 1
B70: D3.2 | C70: ='12.lan'!D169 -> Moderate use of products and services (sufficiency) | D70: =C104 -> 1 | E70: =VLOOKUP(D70,$C$102:$D$106,2,FALSE()) -> medium | F70: ='12.lan'!$D$329 -> Introduce value between 0 and 10 | I70: =IFERROR(J70*H70/10,0) -> 0 | J70: =IFERROR($J$68*K70/(SUM($K$69:$K$70)),0) -> 23.809524 | K70: =VLOOKUP(D70,$C$102:$E$106,3,FALSE()) -> 1 | L70: =VLOOKUP(O70,$C$102:$E$106,3,FALSE()) -> 1 | M70: =VLOOKUP(D70,$C$102:$E$106,3,FALSE()) -> 1 | N70: =IF(L70=M70,"",'12.lan'!$D$240&VLOOKUP(L70,$C$102:$D$106,2,FALSE())&" ("&L70&")") | O70: =C104 -> 1
B71: D3.3 | C71: ='12.lan'!D170 -> Negative aspect: wilful disregard of disproportionate environmental impacts | F71: ='12.lan'!$D$330 -> Introduce negative points between 0 and -200 | I71: =H71*J68/50 -> 0 | J71: =-200*J68/50 -> -190.47619
B72: D4 | C72: ='12.lan'!D171 -> Customer participation and product transparency | D72: =IF(K72="trifft nicht zu",C106,'9. Weighting'!P37) -> 1 | E72: =VLOOKUP(D72,$C$102:$D$106,2,FALSE()) -> medium | F72: =IF(K72="trifft nicht zu","trifft nicht zu",'9. Weighting'!P37) -> 1 | H72: =IF(J72<>0,SUM(I73:I75)/J72,"-") -> -1.1 | I72: =IF(J72=0,0,H72*J72) -> -52.380952 | J72: ='9. Weighting'!P36 -> 47.619048 | K72: =IF(AND(D73="trifft nicht zu",D74="trifft nicht zu"),"trifft nicht zu","") | L72: =VLOOKUP(O72,$C$102:$E$106,3,FALSE()) -> 1 | M72: =VLOOKUP(D72,$C$102:$E$106,3,FALSE()) -> 1 | N72: =IF(L72=M72,"",'12.lan'!$D$240&VLOOKUP(L72,$C$102:$D$106,2,FALSE())&" ("&L72&")") | O72: =IF(K72="trifft nicht zu",C106,'9. Weighting'!P37) -> 1
B73: D4.1 | C73: ='12.lan'!D172 -> Customer participation, joint product development and market research | D73: =C104 -> 1 | E73: =VLOOKUP(D73,$C$102:$D$106,2,FALSE()) -> medium | F73: ='12.lan'!$D$329 -> Introduce value between 0 and 10 | H73: 0 | I73: =IFERROR(J73*H73/10,0) -> 0 | J73: =IFERROR($J$72*K73/(SUM($K$73:$K$74)),0) -> 23.809524 | K73: =VLOOKUP(D73,$C$102:$E$106,3,FALSE()) -> 1 | L73: =VLOOKUP(O73,$C$102:$E$106,3,FALSE()) -> 1 | M73: =VLOOKUP(D73,$C$102:$E$106,3,FALSE()) -> 1 | N73: =IF(L73=M73,"",'12.lan'!$D$240&VLOOKUP(L73,$C$102:$D$106,2,FALSE())&" ("&L73&")") | O73: =C104 -> 1
B74: D4.2 | C74: ='12.lan'!D173 -> Product transparency | D74: =C104 -> 1 | E74: =VLOOKUP(D74,$C$102:$D$106,2,FALSE()) -> medium | F74: ='12.lan'!$D$329 -> Introduce value between 0 and 10 | I74: =IFERROR(J74*H74/10,0) -> 0 | J74: =IFERROR($J$72*K74/(SUM($K$73:$K$74)),0) -> 23.809524 | K74: =VLOOKUP(D74,$C$102:$E$106,3,FALSE()) -> 1 | L74: =VLOOKUP(O74,$C$102:$E$106,3,FALSE()) -> 1 | M74: =VLOOKUP(D74,$C$102:$E$106,3,FALSE()) -> 1 | N74: =IF(L74=M74,"",'12.lan'!$D$240&VLOOKUP(L74,$C$102:$D$106,2,FALSE())&" ("&L74&")") | O74: =C104 -> 1
B75: D4.2 | C75: ='12.lan'!D174 -> Negative aspect: non-disclosure of hazardous substances | F75: ='12.lan'!$D$330 -> Introduce negative points between 0 and -200 | H75: -55 | I75: =H75*J72/50 -> -52.380952 | J75: =-200*J72/50 -> -190.47619
B76: E | C76: ='12.lan'!D175 -> Social environment | D76: =L76 -> 1 | E76: =VLOOKUP(D76,$C$102:$D$106,2,FALSE()) -> medium | H76: =IFERROR(I76/J76,0) -> -0.50875 | I76: =I77+I81+I86+I90 -> -96.904762 | J76: =J77+J81+J86+J90 -> 190.47619 | L76: ='9. Weighting'!K53 -> 1 | N76: =IF(D76<>L76,'12.lan'!$D$240&VLOOKUP(L76,$C$102:$D$106,2,FALSE())&" ("&L76&")","")
B77: E1 | C77: ='12.lan'!D176 -> Purpose of products and services and their effects on society | D77: =IF(K77="trifft nicht zu",C106,'9. Weighting'!M43) -> 1 | E77: =VLOOKUP(D77,$C$102:$D$106,2,FALSE()) -> medium | F77: =IF(K77="trifft nicht zu","trifft nicht zu",'9. Weighting'!M43) -> 1 | H77: =IF(J77<>0,SUM(I78:I80)/J77,"-") -> -2 | I77: =IF(J77=0,0,H77*J77) -> -95.238095 | J77: ='9. Weighting'!M42 -> 47.619048 | K77: =IF(AND(D78="trifft nicht zu",D79="trifft nicht zu"),"trifft nicht zu","") | L77: =VLOOKUP(O77,$C$102:$E$106,3,FALSE()) -> 1 | M77: =VLOOKUP(D77,$C$102:$E$106,3,FALSE()) -> 1 | N77: =IF(L77=M77,"",'12.lan'!$D$240&VLOOKUP(L77,$C$102:$D$106,2,FALSE())&" ("&L77&")") | O77: =IF(K77="trifft nicht zu",C106,'9. Weighting'!M43) -> 1
B78: E1.1 | C78: ='12.lan'!D177 -> Products and services should cover basic needs and contribute to a good life | D78: =C104 -> 1 | E78: =VLOOKUP(D78,$C$102:$D$106,2,FALSE()) -> medium | F78: ='12.lan'!$D$329 -> Introduce value between 0 and 10 | I78: =IFERROR(J78*H78/10,0) -> 0 | J78: =IFERROR($J$77*K78/(SUM($K$78:$K$79)),0) -> 23.809524 | K78: =VLOOKUP(D78,$C$102:$E$106,3,FALSE()) -> 1 | L78: =VLOOKUP(O78,$C$102:$E$106,3,FALSE()) -> 1 | M78: =VLOOKUP(D78,$C$102:$E$106,3,FALSE()) -> 1 | N78: =IF(L78=M78,"",'12.lan'!$D$240&VLOOKUP(L78,$C$102:$D$106,2,FALSE())&" ("&L78&")") | O78: =C104 -> 1
B79: E1.2 | C79: ='12.lan'!D178 -> Social impact of products and services | D79: =C104 -> 1 | E79: =VLOOKUP(D79,$C$102:$D$106,2,FALSE()) -> medium | F79: ='12.lan'!$D$329 -> Introduce value between 0 and 10 | I79: =IFERROR(J79*H79/10,0) -> 0 | J79: =IFERROR($J$77*K79/(SUM($K$78:$K$79)),0) -> 23.809524 | K79: =VLOOKUP(D79,$C$102:$E$106,3,FALSE()) -> 1 | L79: =VLOOKUP(O79,$C$102:$E$106,3,FALSE()) -> 1 | M79: =VLOOKUP(D79,$C$102:$E$106,3,FALSE()) -> 1 | N79: =IF(L79=M79,"",'12.lan'!$D$240&VLOOKUP(L79,$C$102:$D$106,2,FALSE())&" ("&L79&")") | O79: =C104 -> 1
B80: E1.3 | C80: ='12.lan'!D179 -> Negative aspect: unethical and unfit products and services | F80: ='12.lan'!$D$330 -> Introduce negative points between 0 and -200 | H80: -100 | I80: =H80*J77/50 -> -95.238095 | J80: =-200*J77/50 -> -190.47619
B81: E2 | C81: ='12.lan'!D180 -> Contribution to the community | D81: =IF(K81="trifft nicht zu",C106,'9. Weighting'!N43) -> 1.5 | E81: =VLOOKUP(D81,$C$102:$D$106,2,FALSE()) -> high | F81: =IF(K81="trifft nicht zu","trifft nicht zu",'9. Weighting'!N43) -> 1.5 | H81: =IF(J81<>0,SUM(I82:I85)/J81,"-") -> 0 | I81: =IF(J81=0,0,H81*J81) -> 0 | J81: ='9. Weighting'!N42 -> 71.428571 | K81: =IF(AND(D82="trifft nicht zu",D83="trifft nicht zu"),"trifft nicht zu","") | L81: =VLOOKUP(O81,$C$102:$E$106,3,FALSE()) -> 1.5 | M81: =VLOOKUP(D81,$C$102:$E$106,3,FALSE()) -> 1.5 | N81: =IF(L81=M81,"",'12.lan'!$D$240&VLOOKUP(L81,$C$102:$D$106,2,FALSE())&" ("&L81&")") | O81: =IF(K81="trifft nicht zu",C106,'9. Weighting'!N43) -> 1.5
B82: E2.1 | C82: ='12.lan'!D181 -> Taxes and social security contributions | D82: =C104 -> 1 | E82: =VLOOKUP(D82,$C$102:$D$106,2,FALSE()) -> medium | F82: ='12.lan'!$D$329 -> Introduce value between 0 and 10 | I82: =IFERROR(J82*H82/10,0) -> 0 | J82: =IFERROR($J$81*K82/SUM($K$82:$K$83),0) -> 35.714286 | K82: =VLOOKUP(D82,$C$102:$E$106,3,FALSE()) -> 1 | L82: =VLOOKUP(O82,$C$102:$E$106,3,FALSE()) -> 1 | M82: =VLOOKUP(D82,$C$102:$E$106,3,FALSE()) -> 1 | N82: =IF(L82=M82,"",'12.lan'!$D$240&VLOOKUP(L82,$C$102:$D$106,2,FALSE())&" ("&L82&")") | O82: =C104 -> 1
B83: E2.2 | C83: ='12.lan'!D182 -> Voluntary contributions that strengthen society | D83: 1 | E83: =VLOOKUP(D83,$C$102:$D$106,2,FALSE()) -> medium | F83: ='12.lan'!$D$329 -> Introduce value between 0 and 10 | I83: =IFERROR(J83*H83/10,0) -> 0 | J83: =IFERROR($J$81*K83/SUM($K$82:$K$83),0) -> 35.714286 | K83: =VLOOKUP(D83,$C$102:$E$106,3,FALSE()) -> 1 | L83: =VLOOKUP(O83,$C$102:$E$106,3,FALSE()) -> 1 | M83: =VLOOKUP(D83,$C$102:$E$106,3,FALSE()) -> 1 | N83: =IF(L83=M83,"",'12.lan'!$D$240&VLOOKUP(L83,$C$102:$D$106,2,FALSE())&" ("&L83&")") | O83: =C104 -> 1
B84: E2.3 | C84: ='12.lan'!D183 -> Negative aspect: inappropriate non-payment of tax | F84: ='12.lan'!$D$330 -> Introduce negative points between 0 and -200 | I84: =H84*J81/50 -> 0 | J84: =-200*J81/50 -> -285.71429
B85: E2.4 | C85: ='12.lan'!D184 -> Negative aspect: no anti-corruption policy | F85: ='12.lan'!$D$330 -> Introduce negative points between 0 and -200 | H85: 0 | I85: =H85*J81/50 -> 0 | J85: =-200*J81/50 -> -285.71429
B86: E3 | C86: ='12.lan'!D185 -> Reduction of environmental impact | D86: =IF(K86="trifft nicht zu",C106,'9. Weighting'!O43) -> 1 | E86: =VLOOKUP(D86,$C$102:$D$106,2,FALSE()) -> medium | H86: =IF(J86<>0,SUM(I87:I89)/J86,"-") -> -0.06 | I86: =IF(J86=0,0,H86*J86) -> -2.8571429 | J86: ='9. Weighting'!O42 -> 47.619048 | K86: =IF(AND(D87="trifft nicht zu",D88="trifft nicht zu"),"trifft nicht zu","") | L86: =VLOOKUP(O86,$C$102:$E$106,3,FALSE()) -> 1 | M86: =VLOOKUP(D86,$C$102:$E$106,3,FALSE()) -> 1 | N86: =IF(L86=M86,"",'12.lan'!$D$240&VLOOKUP(L86,$C$102:$D$106,2,FALSE())&" ("&L86&")") | O86: =IF(K86="trifft nicht zu",C106,'9. Weighting'!O43) -> 1
B87: E3.1 | C87: ='12.lan'!D186 -> Absolute impact and management strategy | D87: =C104 -> 1 | E87: =VLOOKUP(D87,$C$102:$D$106,2,FALSE()) -> medium | F87: ='12.lan'!$D$329 -> Introduce value between 0 and 10 | I87: =IFERROR(J87*H87/10,0) -> 0 | J87: =IFERROR(J86*K87/SUM($K$87:$K$88),0) -> 23.809524 | K87: =VLOOKUP(D87,$C$102:$E$106,3,FALSE()) -> 1 | L87: =VLOOKUP(O87,$C$102:$E$106,3,FALSE()) -> 1 | M87: =VLOOKUP(D87,$C$102:$E$106,3,FALSE()) -> 1 | N87: =IF(L87=M87,"",'12.lan'!$D$240&VLOOKUP(L87,$C$102:$D$106,2,FALSE())&" ("&L87&")") | O87: =C104 -> 1
B88: E3.2 | C88: ='12.lan'!D187 -> Relative impact | D88: =C104 -> 1 | E88: =VLOOKUP(D88,$C$102:$D$106,2,FALSE()) -> medium | F88: ='12.lan'!$D$329 -> Introduce value between 0 and 10 | I88: =IFERROR(J88*H88/10,0) -> 0 | J88: =IFERROR(J86*K88/SUM($K$87:$K$88),0) -> 23.809524 | K88: =VLOOKUP(D88,$C$102:$E$106,3,FALSE()) -> 1 | L88: =VLOOKUP(O88,$C$102:$E$106,3,FALSE()) -> 1 | M88: =VLOOKUP(D88,$C$102:$E$106,3,FALSE()) -> 1 | N88: =IF(L88=M88,"",'12.lan'!$D$240&VLOOKUP(L88,$C$102:$D$106,2,FALSE())&" ("&L88&")") | O88: =C104 -> 1
B89: E3.3 | C89: ='12.lan'!D188 -> Negative aspect: infringement of environmental regulations and disproportionate environmental pollution | F89: ='12.lan'!$D$330 -> Introduce negative points between 0 and -200 | H89: -3 | I89: =H89*J86/50 -> -2.8571429 | J89: =-200*J86/50 -> -190.47619
B90: E4 | C90: ='12.lan'!D189 -> Social co-determination and transparency | D90: =IF(K90="trifft nicht zu",C106,'9. Weighting'!P43) -> 0.5 | E90: =VLOOKUP(D90,$C$102:$D$106,2,FALSE()) -> low | H90: =IF(J90<>0,SUM(I91:I93)/J90,"-") -> 0.05 | I90: =IF(J90=0,0,H90*J90) -> 1.1904762 | J90: ='9. Weighting'!P42 -> 23.809524 | K90: =IF(AND(D91="trifft nicht zu",D92="trifft nicht zu"),"trifft nicht zu","") | L90: =VLOOKUP(O90,$C$102:$E$106,3,FALSE()) -> 0.5 | M90: =VLOOKUP(D90,$C$102:$E$106,3,FALSE()) -> 0.5 | N90: =IF(L90=M90,"",'12.lan'!$D$240&VLOOKUP(L90,$C$102:$D$106,2,FALSE())&" ("&L90&")") | O90: =IF(K90="trifft nicht zu",C106,'9. Weighting'!P43) -> 0.5
B91: E4.1 | C91: ='12.lan'!D190 -> Transparency | D91: 1 | E91: =VLOOKUP(D91,$C$102:$D$106,2,FALSE()) -> medium | F91: ='12.lan'!$D$329 -> Introduce value between 0 and 10 | I91: =IFERROR(J91*H91/10,0) -> 0 | J91: =IFERROR($J$90*K91/SUM($K$91:$K$92),0) -> 11.904762 | K91: =VLOOKUP(D91,$C$102:$E$106,3,FALSE()) -> 1 | L91: =VLOOKUP(O91,$C$102:$E$106,3,FALSE()) -> 1 | M91: =VLOOKUP(D91,$C$102:$E$106,3,FALSE()) -> 1 | N91: =IF(L91=M91,"",'12.lan'!$D$240&VLOOKUP(L91,$C$102:$D$106,2,FALSE())&" ("&L91&")") | O91: =C104 -> 1
B92: E4.2 | C92: ='12.lan'!D191 -> Social participation | D92: =C104 -> 1 | E92: =VLOOKUP(D92,$C$102:$D$106,2,FALSE()) -> medium | F92: ='12.lan'!$D$329 -> Introduce value between 0 and 10 | H92: 1 | I92: =IFERROR(J92*H92/10,0) -> 1.1904762 | J92: =IFERROR($J$90*K92/SUM($K$91:$K$92),0) -> 11.904762 | K92: =VLOOKUP(D92,$C$102:$E$106,3,FALSE()) -> 1 | L92: =VLOOKUP(O92,$C$102:$E$106,3,FALSE()) -> 1 | M92: =VLOOKUP(D92,$C$102:$E$106,3,FALSE()) -> 1 | N92: =IF(L92=M92,"",'12.lan'!$D$240&VLOOKUP(L92,$C$102:$D$106,2,FALSE())&" ("&L92&")") | O92: =C104 -> 1
B93: E4.3 | C93: ='12.lan'!D192 -> Negative aspect: lack of transparency and wilful misinformation | F93: ='12.lan'!$D$330 -> Introduce negative points between 0 and -200 | I93: =H93*J90/50 -> 0 | J93: =-200*J90/50 -> -95.238095
B95: ='12.lan'!D92 -> Total Balance Score: | H95: =H4 -> -0.38904762 | I95: =I4 -> -389.04762 | J95: =J4 -> 1000
B102: 2 | C102: 2 | D102: ='12.lan'!D97 -> very high | E102: 2
B103: 1.5 | C103: 1.5 | D103: ='12.lan'!D98 -> high | E103: 1.5
B104: 1 | C104: 1 | D104: ='12.lan'!D99 -> medium | E104: 1
B105: 0.5 | C105: 0.5 | D105: ='12.lan'!D100 -> low | E105: 0.5
B106: 0 | C106: 0 | D106: ='12.lan'!D101 -> not applicable | E106: 0

Sheet 9. Weighting
E4: MATRIX 5.0 | K4: VALUES WERTE | M4: 1) HUMAN DIGNITY | N4: 2) SOLIDARITY & JUSTICE | O4: 3) ECOLOGICAL SUSTAINABILITY | P4: 4) DEMOCRATIC CO-DETERMINATION AND TRANSPARENCY
B5: Total Sales (in Mio Euro)
B6: Total Assets (in Mio Euro)
H7: fields necessary to fill out | J7: these field contains a comment on the necesarry information for cells to be filled out or on the weighting in general
F8: STAKEHOLDER BERÜHRUNGSGGRUPPE
M9: =M15+M23+M29+M36+M42 -> 238.09524 | N9: =N15+N23+N29+N36+N42 -> 309.52381 | O9: =O15+O23+O29+O36+O42 -> 297.61905 | P9: =P15+P23+P29+P36+P42 -> 154.7619
F10: Gesamt-Ausgaben an Lieferanten / total expenditures on the supply chain | I10: ='2. Company Facts'!C7 -> 200000 | J10: A: SUPPLIERS | K10: =K49 -> 0.5 | L10: =M15+N15+O15+P15 -> 95.238095 | M10: A1 | N10: A2 | O10: A3 | P10: A4
E12: NACE | F12: Industry | G12: Product / Services Description | H12: Region | I12: Expenditures
E13: =LEFT(F13,2) -> A | F13: ='2. Company Facts'!B10 -> A - Landwirtschaft, Forstwirtschaft und Fischerei | G13: ='2. Company Facts'!C10 -> 0 | H13: ='2. Company Facts'!D10 -> EGY Ägypten | I13: ='2. Company Facts'!F10 -> 3388
E14: =LEFT(F14,2) -> Ca | F14: ='2. Company Facts'!B11 -> Ca - Food production, drinks and tobacco (C10, C11, C12) | G14: ='2. Company Facts'!C11 -> 0 | H14: ='2. Company Facts'!D11 -> AFG Afghanistan | I14: ='2. Company Facts'!F11 -> 654 | M14: ='3. Calc'!D10 -> 1 | N14: ='3. Calc'!D13 -> 1 | O14: ='3. Calc'!D17 -> 1 | P14: ='3. Calc'!D20 -> 1 | Q14: ='11.Region'!U10 -> 0
E15: =LEFT(F15,2) -> A | F15: ='2. Company Facts'!B12 -> A - Landwirtschaft, Forstwirtschaft und Fischerei | G15: ='2. Company Facts'!C12 -> 0 | H15: ='2. Company Facts'!D12 -> DZA Algerien | I15: ='2. Company Facts'!F12 -> 456 | M15: =M49 -> 23.809524 | N15: =N49 -> 23.809524 | O15: =O49 -> 23.809524 | P15: =P49 -> 23.809524
E16: =LEFT(F16,2) -> A | F16: ='2. Company Facts'!B13 -> A - Landwirtschaft, Forstwirtschaft und Fischerei | G16: ='2. Company Facts'!C13 -> 0 | H16: ='2. Company Facts'!D13 -> BGD Bangladesch | I16: ='2. Company Facts'!F13 -> 77 | M16: =IF(G69="empty",1,'3. Calc'!C104) -> 1 | N16: =IF(G69="empty",1,'3. Calc'!C104) -> 1 | O16: =IF(G69="empty",1,IFERROR(IF('11.Region'!N8>1.5,'3. Calc'!C102,IF('11.Region'!N8>1.25,'3. Calc'!C103,IF('11.Region'!N8<0.75,'3. Calc'!C105,'3. Calc'!C104))),'3. Calc'!C104)) -> 1 | P16: =IF(G69="empty",1,IF('11.Region'!I9<1.5,'3. Calc'!C105,IF('11.Region'!I9<3.26,'3. Calc'!C104,IF('11.Region'!I9<4.5,'3. Calc'!C103,'3. Calc'!C102)))) -> 1
E17: =LEFT(F17,2) -> Pl | F17: ='2. Company Facts'!B14 -> Please enter | G17: ='2. Company Facts'!C14 -> 0 | H17: ='2. Company Facts'!D14 -> 0 | I17: ='2. Company Facts'!F14 -> 0
F18: Rest | H18: ='2. Company Facts'!D15 -> QAT Katar | I18: ='2. Company Facts'!F15 -> 195425
F19: profit | I19: ='2. Company Facts'!C18 -> 456456456 | J19: B: INVESTORS | K19: =K50 -> 2 | L19: =M23+N23+O23+P23 -> 428.57143 | M19: B1 | N19: B2 | O19: B3 | P19: B4
F20: profit in % of total Sales | I20: =IFERROR(I19/I32,"-") -> 3681100.5
F21: costs of finance | I21: ='2. Company Facts'!C19 -> 266
E22: =IFERROR((G24+I24)/I23,0.2) -> 1.6904762 | F22: <-- (zugänge anlageverm.+financial assets)/total assets | G22: finance income | I22: ='2. Company Facts'!C20 -> 500 | M22: ='3. Calc'!D24 -> 1 | N22: ='3. Calc'!D28 -> 1.5 | O22: ='3. Calc'!D31 -> 1.5 | P22: ='3. Calc'!D35 -> 0.5
E23: =IFERROR(I32/I23,0.3) -> 0.2952381 | F23: <-- ratio: sales/assets | G23: total assets | I23: ='2. Company Facts'!C21 -> 420 | M23: =M50 -> 95.238095 | N23: =N50 -> 142.85714 | O23: =O50 -> 142.85714 | P23: =P50 -> 47.619048
F24: "zugänge zum anlagevermögen" | G24: ='2. Company Facts'!C22 -> 400 | H24: "invested money" | I24: ='2. Company Facts'!C23 -> 310 | M24: =IF(G69="empty",1,IFERROR(IF(H35='10. Industry'!A22,'3. Calc'!C102,IF(E23<0.1,'3. Calc'!C103,IF(E23>0.5,'3. Calc'!C105,'3. Calc'!C104))),'3. Calc'!C104)) -> 1 | N24: =IF(G69="empty",1,IFERROR(IF(I20="-",'3. Calc'!C104,IF(I20>0.1,'3. Calc'!C103,IF(I20<0.001,'3. Calc'!C106,IF(I20<0.03,'3. Calc'!C105,'3. Calc'!C104)))),'3. Calc'!C104)) -> 1.5 | O24: =IF(G69="empty",1,IFERROR(IF(H35='10. Industry'!A22,'3. Calc'!C102,IF(E22<0.1,'3. Calc'!C105,IF(E22>0.25,'3. Calc'!C103,'3. Calc'!C104))),'3. Calc'!C104)) -> 1.5 | P24: =IF(G69="empty",1,IF(H39='12.lan'!D324,'3. Calc'!C105,'3. Calc'!C104)) -> 0.5
F25: employee expenditures | I25: ='2. Company Facts'!C27 -> 5501 | J25: C: EMPLOYEES | K25: =K51 -> 0.5 | L25: =M29+N29+O29+P29 -> 95.238095 | M25: C1 | N25: C2 | O25: C3 | P25: C4
F26: number of FTE | I26: ='2. Company Facts'!C26 -> 5
G27: % employees in | H27: ='2. Company Facts'!B30 -> ETH Äthiopien | I27: ='2. Company Facts'!D30 -> 0.46
G28: % employees in | H28: ='2. Company Facts'!B31 -> BHR Bahrain | I28: ='2. Company Facts'!D31 -> 0.11 | M28: ='3. Calc'!D39 -> 1 | N28: ='3. Calc'!D44 -> 1 | O28: ='3. Calc'!D49 -> 1.5 | P28: ='3. Calc'!D54 -> 0.5
G29: % employees in | H29: ='2. Company Facts'!B32 -> 0 | I29: ='2. Company Facts'!D32 -> 0 | M29: =M51 -> 23.809524 | N29: =N51 -> 23.809524 | O29: =O51 -> 35.714286 | P29: =P51 -> 11.904762
F30: potential commuting impact | I30: ='2. Company Facts'!C33 -> 456456 | M30: =IF(G69="empty",1,'3. Calc'!C104) -> 1 | N30: =IF(G69="empty",1,'3. Calc'!C104) -> 1 | O30: =IF(G69="empty",1,IF(AND(I31='12.lan'!D53,I30<10),'3. Calc'!C105,IF(I30>25,'3. Calc'!C103,'3. Calc'!C104))) -> 1.5 | P30: =IF(G69="empty",1,IF(I26=1,'3. Calc'!C106,IF(H39='12.lan'!D324,'3. Calc'!C105,IF('11.Region'!I14>3.25,'3. Calc'!C103,'3. Calc'!C104)))) -> 0.5
F31: existence of a company canteen | I31: ='2. Company Facts'!C34 -> no
F32: total sales | I32: ='2. Company Facts'!C37 -> 124 | J32: D: CUSTOMERS | K32: 1 | L32: =M36+N36+O36+P36 -> 190.47619 | M32: D1 | N32: D2 | O32: D3 | P32: D4
H33: B2B / B2C | I33: ='2. Company Facts'!C38 -> ja
F34: Industry | G34: Product / Services Description | H34: industry | I34: % of total sales
F35: ='2. Company Facts'!B41 -> J - Information und Kommunikation | G35: ='2. Company Facts'!C41 -> 0 | H35: =LEFT(F35,2) -> J | I35: ='2. Company Facts'!D41 -> 0.87 | M35: ='3. Calc'!D60 -> 1 | N35: ='3. Calc'!D64 -> 1 | O35: ='3. Calc'!D68 -> 1 | P35: ='3. Calc'!D72 -> 1
F36: ='2. Company Facts'!B42 -> Ce - Pharmaceutical products and preparations (C21) | G36: ='2. Company Facts'!C42 -> abc | H36: =LEFT(F36,2) -> Ce | I36: ='2. Company Facts'!D42 -> 0.13 | M36: =M52 -> 47.619048 | N36: =N52 -> 47.619048 | O36: =O52 -> 47.619048 | P36: =P52 -> 47.619048
F37: ='2. Company Facts'!B43 -> Please enter | G37: ='2. Company Facts'!C43 -> 0 | H37: =LEFT(F37,2) -> Pl | I37: ='2. Company Facts'!D43 -> 0 | M37: =IF(G69="empty",1,'3. Calc'!C104) -> 1 | N37: =IF(G69="empty",1,'3. Calc'!C104) -> 1 | O37: =IF(G69="empty",1,VLOOKUP(S37,'3. Calc'!$B$102:$C$106,2,FALSE())) -> 1 | P37: =IF(G69="empty",1,IFERROR(IF(I33='12.lan'!D52,'3. Calc'!C103,'3. Calc'!C104),'3. Calc'!C104)) -> 1 | S37: =VLOOKUP('10. Industry'!J39,F49:H53,3,FALSE()) -> 1
J38: E: SOCIETY | K38: 1 | L38: =M42+N42+O42+P42 -> 190.47619 | M38: E1 | N38: E2 | O38: E3 | P38: E4
H39: =IF(AND(I26<10,OR(I32<=2000000,I23<=2000000)),'12.lan'!D324,IF(AND(I26<50,OR(I32<=10000000,I23<=10000000)),'12.lan'!D325,IF(AND(I26<250,OR(I32<=50000000,I23<=43000000)),'12.lan'!D326,'12.lan'!D327))) -> Micro-business
F40: Company Size (EU definition) | H40: =IF(AND(I26=0,I32=0,I23=0),'12.lan'!E326) -> 0
M41: ='3. Calc'!D77 -> 1 | N41: ='3. Calc'!D81 -> 1.5 | O41: ='3. Calc'!D86 -> 1 | P41: ='3. Calc'!D90 -> 0.5
M42: =M53 -> 47.619048 | N42: =N53 -> 71.428571 | O42: =O53 -> 47.619048 | P42: =P53 -> 23.809524
M43: =IF(G69="empty",1,'3. Calc'!C104) -> 1 | N43: =IF(G69="empty",1,IF(I20="-",'3. Calc'!C104,IF(I20<0.05,'3. Calc'!C105,IF(I20<0.1,'3. Calc'!C104,IF(I20>0.1,'3. Calc'!C103,'3. Calc'!C104))))) -> 1.5 | O43: =IF(G69="empty",1,VLOOKUP(S37,'3. Calc'!$B$102:$C$106,2,FALSE())) -> 1 | P43: =IF(G69="empty",1,IF(H35="B",'3. Calc'!C103,IF(H35="F",'3. Calc'!C103,IF(H39='12.lan'!D324,'3. Calc'!C105,IF(H39='12.lan'!D324,'3. Calc'!C105,'3. Calc'!C104))))) -> 0.5 | S43: =VLOOKUP('10. Industry'!L39,F49:H53,3,FALSE()) -> 1.5
M45: 1) HUMAN DIGNITY | N45: 2) COOPERATION AND SOLIDARITY | O45: 3) ECOLOGICAL SUSTAINABILITY | P45: 5) DEMOCRATIC CO-DETERMINATION AND TRANSPARENCY
F48: Weighting Points | R48: Selected Weighting
F49: trifft nicht zu | H49: 0 | I49: =IFERROR((60*'11.Region'!G3/('11.Region'!G3+'11.Region'!G10+(I19+I21+I22+G24))*5),100) -> 0.13178786 | J49: =IF(I49<60,60,IF(I49>300,300,I49)) -> 60 | K49: =IFERROR(IF(J49=60,0.5,IF(J49=300,2,IF(J49<180,1,1.5))),1) -> 0.5 | M49: =M62/$Q$67*1000 -> 23.809524 | N49: =N62/$Q$67*1000 -> 23.809524 | O49: =O62/$Q$67*1000 -> 23.809524 | P49: =P62/$Q$67*1000 -> 23.809524 | Q49: =SUM(M49:P49) -> 95.238095 | R49: ='3. Calc'!D9 -> 0.5
F50: niedrig | H50: 0.5 | I50: =IFERROR((60*(I19+I21+I22+G24)/('11.Region'!G3+'11.Region'!G10+(I19+I21+I22+G24))*10),100) -> 599.72917 | J50: =IF(I50<60,60,IF(I50>300,300,I50)) -> 300 | K50: =IFERROR(IF(J50=60,0.5,IF(J50=300,2,IF(J50<180,1,1.5))),1) -> 2 | M50: =M63/$Q$67*1000 -> 95.238095 | N50: =N63/$Q$67*1000 -> 142.85714 | O50: =O63/$Q$67*1000 -> 142.85714 | P50: =P63/$Q$67*1000 -> 47.619048 | Q50: =SUM(M50:P50) -> 428.57143 | R50: ='3. Calc'!D23 -> 2
F51: mittel | H51: 1 | I51: =IFERROR((60*'11.Region'!G10/('11.Region'!G3+'11.Region'!G10+(I19+I21+I22+G24))*10),100) -> 0.0072496504 | J51: =IF(I51<60,60,IF(I51>300,300,I51)) -> 60 | K51: =IFERROR(IF(J51=60,0.5,IF(J51=300,2,IF(J51<180,1,1.5))),1) -> 0.5 | M51: =M64/$Q$67*1000 -> 23.809524 | N51: =N64/$Q$67*1000 -> 23.809524 | O51: =O64/$Q$67*1000 -> 35.714286 | P51: =P64/$Q$67*1000 -> 11.904762 | Q51: =SUM(M51:P51) -> 95.238095 | R51: ='3. Calc'!D38 -> 0.5
F52: hoch | H52: 1.5 | K52: =K32 -> 1 | M52: =M65/$Q$67*1000 -> 47.619048 | N52: =N65/$Q$67*1000 -> 47.619048 | O52: =O65/$Q$67*1000 -> 47.619048 | P52: =P65/$Q$67*1000 -> 47.619048 | Q52: =SUM(M52:P52) -> 190.47619 | R52: ='3. Calc'!D59 -> 1
F53: sehr hoch | H53: 2 | K53: =K38 -> 1 | M53: =M66/$Q$67*1000 -> 47.619048 | N53: =N66/$Q$67*1000 -> 71.428571 | O53: =O66/$Q$67*1000 -> 47.619048 | P53: =P66/$Q$67*1000 -> 23.809524 | Q53: =SUM(M53:P53) -> 190.47619 | R53: ='3. Calc'!D76 -> 1
M54: =SUM(M49:M53) -> 238.09524 | N54: =SUM(N49:N53) -> 309.52381 | O54: =SUM(O49:O53) -> 297.61905 | P54: =SUM(P49:P53) -> 154.7619 | Q54: =SUM(Q49:Q53) -> 1000
M59: 1) HUMAN DIGNITY | N59: 2) COOPERATION AND SOLIDARITY | O59: 3) ECOLOGICAL SUSTAINABILITY | P59: 5) DEMOCRATIC CO-DETERMINATION AND TRANSPARENCY
M61: 1 | N61: 1 | O61: 1 | P61: 1
K62: =IF(K49=R49,K49,R49) -> 0.5 | M62: =M14*$K$62 -> 0.5 | N62: =N14*$K$62 -> 0.5 | O62: =O14*$K$62 -> 0.5 | P62: =P14*$K$62 -> 0.5 | Q62: =SUM(M62:P62) -> 2
K63: =IF(K50=R50,K50,R50) -> 2 | M63: =M22*$K$63 -> 2 | N63: =N22*$K$63 -> 3 | O63: =O22*$K$63 -> 3 | P63: =P22*$K$63 -> 1 | Q63: =SUM(M63:P63) -> 9
K64: =IF(K51=R51,K51,R51) -> 0.5 | M64: =M28*$K$64 -> 0.5 | N64: =N28*$K$64 -> 0.5 | O64: =O28*$K$64 -> 0.75 | P64: =P28*$K$64 -> 0.25 | Q64: =SUM(M64:P64) -> 2
K65: =IF(K52=R52,K52,R52) -> 1 | M65: =M35*K65 -> 1 | N65: =N35*K65 -> 1 | O65: =O35*K65 -> 1 | P65: =P35*K65 -> 1 | Q65: =SUM(M65:P65) -> 4
K66: =IF(K53=R53,K53,R53) -> 1 | M66: =M41*K66 -> 1 | N66: =N41*K66 -> 1.5 | O66: =O41*K66 -> 1 | P66: =P41*K66 -> 0.5 | Q66: =SUM(M66:P66) -> 4
M67: =SUM(M62:M66) -> 5 | N67: =SUM(N62:N66) -> 6.5 | O67: =SUM(O62:O66) -> 6.25 | P67: =SUM(P62:P66) -> 3.25 | Q67: =SUM(Q62:Q66) -> 21
F69: No data in company facts | G69: =IF(AND('2. Company Facts'!C7=0,'2. Company Facts'!F10=0,'2. Company Facts'!F11=0,'2. Company Facts'!F12=0,'2. Company Facts'!F13=0,'2. Company Facts'!F14=0,'2. Company Facts'!C18=0,'2. Company Facts'!C19=0,'2. Company Facts'!C20=0,'2. Company Facts'!C21=0,'2. Company Facts'!C22=0,'2. Company Facts'!C23=0,'2. Company Facts'!C26=0,'2. Company Facts'!C27=0,'2. Company Facts'!D30=0,'2. Company Facts'!D31=0,'2. Company Facts'!D32=0,'2. Company Facts'!C33=0,'2. Company Facts'!C34=0,'2. Company Facts'!C37=0,'2. Company Facts'!C38=0,'2. Company Facts'!D41=0,'2. Company Facts'!D42=0,'2. Company Facts'!D43=0),"empty","data") -> data
B70: DIFFERENCE TO MATRIX 4.0 WEIGHTING

Sheet 4. ECG-Matrix
B2: ='12.lan'!D91&" - "&'0. Intro'!B3&" "&'0. Intro'!C3 -> Common Good Balance Calculator - Version 5.06 | I2: ='12.lan'!D212 -> Note: This is not a certificate.
B3: ='12.lan'!D213 -> COMMON GOOD MATRIX
I4: ='12.lan'!D92 -> Total Balance Score: | K4: ='3. Calc'!I4 -> -389.04762 | M4: ='12.lan'!D214&" "&'3. Calc'!$J$4&'12.lan'!D215 -> of 1000 points
B5: ='12.lan'!D82&": "&'1. General'!C6&"; "&'12.lan'!D83&": "&'1. General'!C12 -> Company / Organisation: LuftGewinn; Period under review: 01.01.2019 - 31.12.2019
B7: ='12.lan'!D206 -> Values ► Stakekolders ▼ | C7: ='12.lan'!D216 -> Human dignity | G7: ='12.lan'!D217 -> Solidarity & social justice | K7: ='12.lan'!D218 -> Environmental sustainability | O7: ='12.lan'!D219 -> Transparency & co-determination
B8: ="A: "&'12.lan'!D108 -> A: Suppliers | C8: ='12.lan'!B109 -> A1: Human dignity in the supply chain | G8: ='12.lan'!B112 -> A2: Solidarity and social justice in the supply chain | K8: ='12.lan'!B116 -> A3: Environmental sustainability in the supply chain | O8: ='12.lan'!B119 -> A4: Transparency & co-determination in the supply chain
C9: ='3. Calc'!I10 -> -42.857143 | D9: ='12.lan'!$D$214 -> of | E9: ='3. Calc'!J10 -> 23.809524 | F9: ='3. Calc'!H10 -> -1.8 | G9: ='3. Calc'!I13 -> -42.857143 | H9: ='12.lan'!$D$214 -> of | I9: ='3. Calc'!J13 -> 23.809524 | J9: ='3. Calc'!H13 -> -1.8 | K9: ='3. Calc'!I17 -> 2.3809524 | L9: ='12.lan'!$D$214 -> of | M9: ='3. Calc'!J17 -> 23.809524 | N9: ='3. Calc'!H17 -> 0.1 | O9: ='3. Calc'!I20 -> 0 | P9: ='12.lan'!$D$214 -> of | Q9: ='3. Calc'!J20 -> 23.809524 | R9: ='3. Calc'!H20 -> 0
B10: ="B: "&'12.lan'!D122 -> B: Owners, equity- and financial service providers | C10: ='12.lan'!B123 -> B1: Ethical position in relation to financial resources | G10: ='12.lan'!B127 -> B2: Social position in relation to financial resources | K10: ='12.lan'!B130 -> B3: Use of funds in relation to social and environmental impacts | O10: ='12.lan'!B134&IF('9. Weighting'!I28=1,'12.lan'!D211,"") -> B4: Ownership and co-determination
C11: ='3. Calc'!I24 -> 15.873016 | D11: ='12.lan'!$D$214 -> of | E11: ='3. Calc'!J24 -> 95.238095 | F11: ='3. Calc'!H24 -> 0.16666667 | G11: ='3. Calc'!I28 -> 0 | H11: ='12.lan'!$D$214 -> of | I11: ='3. Calc'!J28 -> 142.85714 | J11: ='3. Calc'!H28 -> 0 | K11: ='3. Calc'!I31 -> 0 | L11: ='12.lan'!$D$214 -> of | M11: ='3. Calc'!J31 -> 142.85714 | N11: ='3. Calc'!H31 -> 0 | O11: ='3. Calc'!I35 -> 0 | P11: ='12.lan'!$D$214 -> of | Q11: ='3. Calc'!J35 -> 47.619048 | R11: ='3. Calc'!H35 -> 0
B12: ="C: "&'12.lan'!D137 -> C: Employees | C12: ='12.lan'!B138 -> C1: Human dignity in the workplace and working environment | G12: ='12.lan'!B143 -> C2: Self-determined working arrangements | K12: ='12.lan'!B148 -> C3: Environmentally-friendly behaviour of staff | O12: ='12.lan'!B153 -> C4: Co-determination and transparency within the organisation
C13: ='3. Calc'!I39 -> 0.79365079 | D13: ='12.lan'!$D$214 -> of | E13: ='3. Calc'!J39 -> 23.809524 | F13: ='3. Calc'!H39 -> 0.033333333 | G13: ='3. Calc'!I44 -> -0.47619048 | H13: ='12.lan'!$D$214 -> of | I13: ='3. Calc'!J44 -> 23.809524 | J13: ='3. Calc'!H44 -> -0.02 | K13: ='3. Calc'!I49 -> -10.714286 | L13: ='12.lan'!$D$214 -> of | M13: ='3. Calc'!J49 -> 35.714286 | N13: ='3. Calc'!H49 -> -0.3 | O13: ='3. Calc'!I54 -> 0 | P13: ='12.lan'!$D$214 -> of | Q13: ='3. Calc'!J54 -> 11.904762 | R13: ='3. Calc'!H54 -> 0
B14: ="D: "&'12.lan'!D158 -> D: Customers and other companies | C14: ='12.lan'!B159 -> D1: Ethical customer relations | G14: ='12.lan'!B163 -> D2: Cooperation and solidarity with other companies | K14: ='12.lan'!B167 -> D3: Impact on the environment of the use and disposal of products and services | O14: ='12.lan'!B171 -> D4: Customer participation and product transparency
C15: ='3. Calc'!I60 -> -161.90476 | D15: ='12.lan'!$D$214 -> of | E15: ='3. Calc'!J60 -> 47.619048 | F15: ='3. Calc'!H60 -> -3.4 | G15: ='3. Calc'!I64 -> 0 | H15: ='12.lan'!$D$214 -> of | I15: ='3. Calc'!J64 -> 47.619048 | J15: ='3. Calc'!H64 -> 0 | K15: ='3. Calc'!I68 -> 0 | L15: ='12.lan'!$D$214 -> of | M15: ='3. Calc'!J68 -> 47.619048 | N15: ='3. Calc'!H68 -> 0 | O15: ='3. Calc'!I72 -> -52.380952 | P15: ='12.lan'!$D$214 -> of | Q15: ='3. Calc'!J72 -> 47.619048 | R15: ='3. Calc'!H72 -> -1.1
B16: ="E: "&'12.lan'!D175 -> E: Social environment | C16: ='12.lan'!B176 -> E1: Purpose of products and services and their effects on society | G16: ='12.lan'!B180 -> E2: Contribution to the community | K16: ='12.lan'!B185 -> E3: Reduction of environmental impact | O16: ='12.lan'!B189 -> E4: Social co-determination and transparency
C17: ='3. Calc'!I77 -> -95.238095 | D17: ='12.lan'!$D$214 -> of | E17: ='3. Calc'!J77 -> 47.619048 | F17: ='3. Calc'!H77 -> -2 | G17: ='3. Calc'!I81 -> 0 | H17: ='12.lan'!$D$214 -> of | I17: ='3. Calc'!J81 -> 71.428571 | J17: ='3. Calc'!H81 -> 0 | K17: ='3. Calc'!I86 -> -2.8571429 | L17: ='12.lan'!$D$214 -> of | M17: ='3. Calc'!J86 -> 47.619048 | N17: ='3. Calc'!H86 -> -0.06 | O17: ='3. Calc'!I90 -> 1.1904762 | P17: ='12.lan'!$D$214 -> of | Q17: ='3. Calc'!J90 -> 23.809524 | R17: ='3. Calc'!H90 -> 0.05
B19: ='12.lan'!D46 -> Please note that the format of the numbers in the matrix is rounded

Sheet 5. Values
B2: ='12.lan'!D91&" - "&'0. Intro'!B3&" "&'0. Intro'!C3 -> Common Good Balance Calculator - Version 5.06
B3: ='12.lan'!D241&'1. General'!C6 -> Values star for LuftGewinn
B17: ='12.lan'!D221 -> BALANCE OVERVIEW
B18: ='12.lan'!D216 -> Human dignity | C18: ='4. ECG-Matrix'!C9+'4. ECG-Matrix'!C11+'4. ECG-Matrix'!C13+'4. ECG-Matrix'!C15+'4. ECG-Matrix'!C17 -> -283.33333 | D18: ='12.lan'!$D$214 -> of | E18: ='4. ECG-Matrix'!E9+'4. ECG-Matrix'!E11+'4. ECG-Matrix'!E13+'4. ECG-Matrix'!E15+'4. ECG-Matrix'!E17 -> 238.09524 | F18: =C18/E18 -> -1.19 | G18: =IF(F18<0,0,F18) -> 0
B19: ='12.lan'!D217 -> Solidarity & social justice | C19: ='4. ECG-Matrix'!G9+'4. ECG-Matrix'!G11+'4. ECG-Matrix'!G13+'4. ECG-Matrix'!G15+'4. ECG-Matrix'!G17 -> -43.333333 | D19: ='12.lan'!$D$214 -> of | E19: ='4. ECG-Matrix'!I9+'4. ECG-Matrix'!I11+'4. ECG-Matrix'!I13+'4. ECG-Matrix'!I15+'4. ECG-Matrix'!I17 -> 309.52381 | F19: =C19/E19 -> -0.14 | G19: =IF(F19<0,0,F19) -> 0
B20: ='12.lan'!D218 -> Environmental sustainability | C20: ='4. ECG-Matrix'!K9+'4. ECG-Matrix'!K11+'4. ECG-Matrix'!K13+'4. ECG-Matrix'!K15+'4. ECG-Matrix'!K17 -> -11.190476 | D20: ='12.lan'!$D$214 -> of | E20: ='4. ECG-Matrix'!M9+'4. ECG-Matrix'!M11+'4. ECG-Matrix'!M13+'4. ECG-Matrix'!M15+'4. ECG-Matrix'!M17 -> 297.61905 | F20: =C20/E20 -> -0.0376 | G20: =IF(F20<0,0,F20) -> 0
B21: ='12.lan'!D219 -> Transparency & co-determination | C21: ='4. ECG-Matrix'!O9+'4. ECG-Matrix'!O11+'4. ECG-Matrix'!O13+'4. ECG-Matrix'!O15+'4. ECG-Matrix'!O17 -> -51.190476 | D21: ='12.lan'!$D$214 -> of | E21: ='4. ECG-Matrix'!Q9+'4. ECG-Matrix'!Q11+'4. ECG-Matrix'!Q13+'4. ECG-Matrix'!Q15+'4. ECG-Matrix'!Q17 -> 154.7619 | F21: =C21/E21 -> -0.33076923 | G21: =IF(F21<0,0,F21) -> 0
B22: ='12.lan'!D228 -> TOTAL | C22: ='3. Calc'!I4 -> -389.04762 | D22: ='12.lan'!$D$214 -> of | E22: ='3. Calc'!J4 -> 1000 | F22: =C22/E22 -> -0.38904762

Sheet 6. Stakeholder
B2: ='12.lan'!D91&" - "&'0. Intro'!B3&" "&'0. Intro'!C3 -> Common Good Balance Calculator - Version 5.06
B3: ='12.lan'!D242&'1. General'!C6 -> Group star for LuftGewinn
B17: ='12.lan'!D221 -> BALANCE OVERVIEW
B18: ='12.lan'!D108 -> Suppliers | C18: ='3. Calc'!I9 -> -83.333333 | D18: ='12.lan'!$D$214 -> of | E18: ='3. Calc'!J9 -> 95.238095 | F18: =C18/E18 -> -0.875 | G18: =IF(F18<0,0,F18) -> 0
B19: ='12.lan'!D122 -> Owners, equity- and financial service providers | C19: ='3. Calc'!I23 -> 15.873016 | D19: ='12.lan'!$D$214 -> of | E19: ='3. Calc'!J23 -> 428.57143 | F19: =C19/E19 -> 0.037037037 | G19: =IF(F19<0,0,F19) -> 0.037037037
B20: ='12.lan'!D137 -> Employees | C20: ='3. Calc'!I38 -> -10.396825 | D20: ='12.lan'!$D$214 -> of | E20: ='3. Calc'!J38 -> 95.238095 | F20: =C20/E20 -> -0.10916667 | G20: =IF(F20<0,0,F20) -> 0
B21: ='12.lan'!D158 -> Customers and other companies | C21: ='3. Calc'!I59 -> -214.28571 | D21: ='12.lan'!$D$214 -> of | E21: ='3. Calc'!J59 -> 190.47619 | F21: =C21/E21 -> -1.125 | G21: =IF(F21<0,0,F21) -> 0
B22: ='12.lan'!D175 -> Social environment | C22: ='3. Calc'!I76 -> -96.904762 | D22: ='12.lan'!$D$214 -> of | E22: ='3. Calc'!J76 -> 190.47619 | F22: =C22/E22 -> -0.50875 | G22: =IF(F22<0,0,F22) -> 0
B23: ='12.lan'!D228 -> TOTAL | C23: ='3. Calc'!I4 -> -389.04762 | D23: ='12.lan'!$D$214 -> of | E23: ='3. Calc'!J4 -> 1000 | F23: =C23/E23 -> -0.38904762

Sheet 7. Topics
B2: ='12.lan'!D91&" - "&'0. Intro'!B3&" "&'0. Intro'!C3 -> Common Good Balance Calculator - Version 5.06
B3: ='12.lan'!D243&'1. General'!C6 -> Theme star for LuftGewinn
B17: ='12.lan'!D221 -> BALANCE OVERVIEW
B18: A1 | C18: ='4. ECG-Matrix'!C9 -> -42.857143 | D18: ='12.lan'!$D$214 -> of | E18: ='4. ECG-Matrix'!E9 -> 23.809524 | F18: =C18/E18 -> -1.8 | G18: =IF(F18<0,0,F18) -> 0
B19: A2 | C19: ='4. ECG-Matrix'!G9 -> -42.857143 | D19: ='12.lan'!$D$214 -> of | E19: ='4. ECG-Matrix'!I9 -> 23.809524 | F19: =C19/E19 -> -1.8 | G19: =IF(F19<0,0,F19) -> 0
B20: A3 | C20: ='4. ECG-Matrix'!K9 -> 2.3809524 | D20: ='12.lan'!$D$214 -> of | E20: ='4. ECG-Matrix'!M9 -> 23.809524 | F20: =C20/E20 -> 0.1 | G20: =IF(F20<0,0,F20) -> 0.1
B21: A4 | C21: ='4. ECG-Matrix'!O9 -> 0 | D21: ='12.lan'!$D$214 -> of | E21: ='4. ECG-Matrix'!Q9 -> 23.809524 | F21: =C21/E21 -> 0 | G21: =IF(F21<0,0,F21) -> 0
B22: B1 | C22: ='4. ECG-Matrix'!C11 -> 15.873016 | D22: ='12.lan'!$D$214 -> of | E22: ='4. ECG-Matrix'!E11 -> 95.238095 | F22: =C22/E22 -> 0.16666667 | G22: =IF(F22<0,0,F22) -> 0.16666667
B23: B2 | C23: ='4. ECG-Matrix'!G11 -> 0 | D23: ='12.lan'!$D$214 -> of | E23: ='4. ECG-Matrix'!I11 -> 142.85714 | F23: =C23/E23 -> 0 | G23: =IF(F23<0,0,F23) -> 0
B24: B3 | C24: ='4. ECG-Matrix'!K11 -> 0 | D24: ='12.lan'!$D$214 -> of | E24: ='4. ECG-Matrix'!M11 -> 142.85714 | F24: =C24/E24 -> 0 | G24: =IF(F24<0,0,F24) -> 0
B25: B4 | C25: ='4. ECG-Matrix'!O11 -> 0 | D25: ='12.lan'!$D$214 -> of | E25: ='4. ECG-Matrix'!Q11 -> 47.619048 | F25: =C25/E25 -> 0 | G25: =IF(F25<0,0,F25) -> 0
B26: C1 | C26: ='4. ECG-Matrix'!C13 -> 0.79365079 | D26: ='12.lan'!$D$214 -> of | E26: ='4. ECG-Matrix'!E13 -> 23.809524 | F26: =C26/E26 -> 0.033333333 | G26: =IF(F26<0,0,F26) -> 0.033333333
B27: C2 | C27: ='4. ECG-Matrix'!G13 -> -0.47619048 | D27: ='12.lan'!$D$214 -> of | E27: ='4. ECG-Matrix'!I13 -> 23.809524 | F27: =C27/E27 -> -0.02 | G27: =IF(F27<0,0,F27) -> 0
B28: C3 | C28: ='4. ECG-Matrix'!K13 -> -10.714286 | D28: ='12.lan'!$D$214 -> of | E28: ='4. ECG-Matrix'!M13 -> 35.714286 | F28: =C28/E28 -> -0.3 | G28: =IF(F28<0,0,F28) -> 0
B29: C4 | C29: ='4. ECG-Matrix'!O13 -> 0 | D29: ='12.lan'!$D$214 -> of | E29: ='4. ECG-Matrix'!Q13 -> 11.904762 | F29: =C29/E29 -> 0 | G29: =IF(F29<0,0,F29) -> 0
B30: D1 | C30: ='4. ECG-Matrix'!C15 -> -161.90476 | D30: ='12.lan'!$D$214 -> of | E30: ='4. ECG-Matrix'!E15 -> 47.619048 | F30: =C30/E30 -> -3.4 | G30: =IF(F30<0,0,F30) -> 0
B31: D2 | C31: ='4. ECG-Matrix'!G15 -> 0 | D31: ='12.lan'!$D$214 -> of | E31: ='4. ECG-Matrix'!I15 -> 47.619048 | F31: =C31/E31 -> 0 | G31: =IF(F31<0,0,F31) -> 0
B32: D3 | C32: ='4. ECG-Matrix'!K15 -> 0 | D32: ='12.lan'!$D$214 -> of | E32: ='4. ECG-Matrix'!M15 -> 47.619048 | F32: =C32/E32 -> 0 | G32: =IF(F32<0,0,F32) -> 0
B33: D4 | C33: ='4. ECG-Matrix'!O15 -> -52.380952 | D33: ='12.lan'!$D$214 -> of | E33: ='4. ECG-Matrix'!Q15 -> 47.619048 | F33: =C33/E33 -> -1.1 | G33: =IF(F33<0,0,F33) -> 0
B34: E1 | C34: ='4. ECG-Matrix'!C17 -> -95.238095 | D34: ='12.lan'!$D$214 -> of | E34: ='4. ECG-Matrix'!E17 -> 47.619048 | F34: =C34/E34 -> -2 | G34: =IF(F34<0,0,F34) -> 0
B35: E2 | C35: ='4. ECG-Matrix'!G17 -> 0 | D35: ='12.lan'!$D$214 -> of | E35: ='4. ECG-Matrix'!I17 -> 71.428571 | F35: =C35/E35 -> 0 | G35: =IF(F35<0,0,F35) -> 0
B36: E3 | C36: ='4. ECG-Matrix'!K17 -> -2.8571429 | D36: ='12.lan'!$D$214 -> of | E36: ='4. ECG-Matrix'!M17 -> 47.619048 | F36: =C36/E36 -> -0.06 | G36: =IF(F36<0,0,F36) -> 0
B37: E4 | C37: ='4. ECG-Matrix'!O17 -> 1.1904762 | D37: ='12.lan'!$D$214 -> of | E37: ='4. ECG-Matrix'!Q17 -> 23.809524 | F37: =C37/E37 -> 0.05 | G37: =IF(F37<0,0,F37) -> 0.05
B38: ='12.lan'!D228 -> TOTAL | C38: ='3. Calc'!I4 -> -389.04762 | D38: ='12.lan'!$D$214 -> of | E38: ='3. Calc'!J4 -> 1000 | F38: =C38/E38 -> -0.38904762

Sheet 8. Descr.Weighting
A1: ='12.lan'!D91&" - "&'0. Intro'!B3&" "&'0. Intro'!C3 -> Common Good Balance Calculator - Version 5.06
A2: ='12.lan'!D204 -> Description of the weighting model
A4: ='12.lan'!D208 -> General | C4: ='12.lan'!D244 -> The allocation of equal and fixed scores for all companies has been the subject of much discussion within the Matrix-development team during the past few years. Outside sources have also raised many questions and provided feedback. Untill now, the way points are distributed for themes has been the same for all companies (with the exception of one-person companies), regardless of company size, industry and other parameters (regional background, B2B versus B2C, etc.). However, these variables may well have an effect on the relevance to and effect on the common good.For example, the supply chain of an electronics trading company (A1-A4) is more significant than for a mining company, which, in turn, leaves a huge, direct environmental impact, amongst other things (E3). The new weighting model addresses these issues and highlights the significant factors. A survey on the changes was conducted, with feedback clearly favouring a new approach.
A5: ='12.lan'!D207 -> Stakekolders & values | C5: ='12.lan'!D245 -> For the weighting of three stakeholder groups, A) suppliers, B) investors and C) employees, the matrix takes into account the following financial flows to these stakeholders: A) procurement expenditure, B) profit and borrowing costs C) wages and salaries. We are aware of the limited significance attached to money in the current matrix and have plans for how this can be improved in the future. At the same time, this information is readily available in companies' financial balance sheets, and easily meets the needs of many companies. Since taxes and borrowing costs are included in procurement expenditure, these account for only 50% of the weighting.
A6: ='12.lan'!D205 -> Themes | C6: ='12.lan'!D246 -> There are also criteria for the weighting of the themes, for example a company's size or industry or the relevant local employment law. The United Nations' International Standard Industrial Classification of All Economic Activities (ISIC Rev.4) is used for all industry sector definitions. For size classification, definitions as set out by the EU are used. The table below summarises the current weighting factors (as at May 2017):
A7: A1 | C7: -
A8: A2 | C8: ='12.lan'!D248 -> -
A9: A3 | C9: ='12.lan'!D249 -> The weighting of this theme is dependent on the environmental effect of the supplier's sector (see sheet “Industry").
A10: A4 | C10: ='12.lan'!D250 -> The weighting of this theme is dependent on co-determination rights in the countries of the most important supply industries (based on the ILUC index of the International Labour Union).
A11: B1 | C11: ='12.lan'!D251 -> The weighting of this theme depends on the ratio turnover to the balance sheet total.
A12: B2 | C12: ='12.lan'!D252 -> The weighting of this theme depends on the ratio profit to turnover
A13: B3 | C13: ='12.lan'!D253 -> The weighting of this theme is dependent on additions to fixed-assets and financial assets in relation to the balance sheet total.
A14: B4 | C14: ='12.lan'!D254 -> The weighting of this theme is dependent on the size of the company.
A15: C1 | C15: ='12.lan'!D255 -> -
A16: C2 | C16: ='12.lan'!D256 -> -
A17: C3 | C17: ='12.lan'!D257 -> The weighting of this theme is dependent on the existence of a canteen for most of the employees as well as an (estimated) average commute to work.
A18: C4 | C18: ='12.lan'!D258 -> The weighting of this theme is dependent on company size and co-determination rights in the countries of the most important supply industries (based on the ILUC index of the International Labour Union).
A19: D1 | C19: ='12.lan'!D259 -> -
... A26: E4 | C26: ='12.lan'!D266 -> The weighting of this theme depends on the company size and the industry sector.

Sheet 9. Change-Management
A1: Version | B1: Changes
A2: 5.02 | B2: Spanish, Italian and English added
A3: 5.03 | B3: Change format of numbers so it works globally. There were some problems in Switzerland
A4: 5.04 | B4: Add possibility of changing the weighting by stakeholder (not only themes and aspects)
A5: 5.05 | B5: Update ITUC index and PPP index for weighting Delete rounding in some formulas. The rounding should be visible but the number stays so that the calculations are not affected. Info added about the rounding. French added
A6: 5.06 | B6: Wrong formula while considering the size of the company for the weighting in B4, C4 and E4. If there is no data in Company Facts, weighting is equally weighted. Pink conditional formatting when "canteen" and "b2b/c" field in company facts is zero. Improve editing of new languages (consistency in formulas is assured)

Sheet 10. Industry
A1: INDUSTRY WEIGHTING - COMMON GOOD MATRIX
B2: INDUSTRY | E2: A1 -social risks in the Supply Chain | G2: A3 -ecological sustainability in the Supply Chain | I2: D3 - Ecological Design of products and services | K2: E3 - Reduction of Environmental Impact | M2: E4 - Social transparency and co- determination | O2: A3 - Ecologicla Supply Chain Risk
B3: (based UN International Standard Industrial Classification of All Economic Activities, Rev.4 -http://unstats.un.org/unsd/cr/registry/regcst.asp?Cl=27) | E3: weighting | F3: argumentation: based on the social risks in the industry | G3: weighting | H3: argumentation: based on ecological impact on the planterary boundaries in the supply cahin (studies and the use of quantitative models - e.g. ecological footprint - will be applied herefor) | I3: weighting | J3: argumentation: based on the products / service impact on the planterary boundaries in the use phase (studies and the use of quantitative models - e.g. ecological footprint - will be applied herefor) | K3: weighting | L3: argumentation: based on the sectors direct impact in the production phase on the planterary boundaries (studies and the use of quantitative models will be applied herefor); e.g. sehr hoch: The sector has a major impact of various planetary boundaries | M3: weighting | N3: argumentation: the weighting is depending on the impact the industry has particularly on the adjacent environment | P3: weighting | Q3: argumentation: based on the sectors direct impact in the production phase on the planterary boundaries (studies and the use of quantitative models will be applied herefor) sehr hoch: The sector has a major impact of various planetary boundaries
A4: A | B4: ='12.lan'!D268 -> A - agriculture, forestry management, fishing industry | E4: sehr hoch | H4: ist E3? | I4: mittel | J4: the main impacts are in the production phase | K4: sehr hoch | L4: major direct impact on various planetary boundaries in the production (climate change, N/P-cycle, biodiversity, land-use-change) | M4: mittel | P4: sehr hoch
A5: B | B5: ='12.lan'!D269 -> B - Mining and quarrying | E5: sehr hoch | I5: mittel | K5: sehr hoch | L5: major impact on eco-systems | M5: sehr hoch | P5: sehr hoch
A6: C | B6: ='12.lan'!D270 -> C - Manufacturing industries (not further specified) | E6: hoch | I6: mittel | K6: hoch | L6: Please note: This industry is very heterogen. | M6: hoch | P6: hoch
A7: Ca | B7: ='12.lan'!D271 -> Ca - Food production, drinks and tobacco (C10, C11, C12) | E7: sehr hoch | I7: mittel | K7: mittel | M7: mittel | P7: sehr hoch
A8: Cb | B8: ='12.lan'!D272 -> Cb - Textile production, clothing, leather and leather products (C13, C14, C15) | E8: sehr hoch | I8: mittel | K8: hoch | M8: mittel | P8: sehr hoch
A9: Cc | B9: ='12.lan'!D273 -> Cc - Paper and forest products, also printed matter (C16, C17, C18) | E9: hoch | I9: mittel | K9: hoch | M9: mittel | P9: sehr hoch
A10: Cd | B10: ='12.lan'!D274 -> Cd - Production of petrochemical products and plastics (C19, C20;C22) | E10: sehr hoch | I10: mittel | K10: hoch | M10: hoch | P10: sehr hoch
A11: Ce | B11: ='12.lan'!D275 -> Ce - Pharmaceutical products and preparations (C21) | E11: mittel | I11: hoch | J11: residues for some pharmaproducts critical | K11: hoch | M11: hoch | P11: hoch
A12: Cf | B12: ='12.lan'!D276 -> Cf - Production of non-metallic minerals (C23) | E12: hoch | I12: mittel | K12: hoch | M12: hoch | P12: hoch
A13: Cg | B13: ='12.lan'!D277 -> Cg - Production of metal and metallic products (excl. machines and equipment) (C24, C25) | E13: sehr hoch | I13: mittel | K13: hoch | M13: hoch | P13: sehr hoch
A14: Ch | B14: ='12.lan'!D278 -> Ch - Production of electronic equipment, instruments and components as well as computers (C26, C27, C28) | E14: sehr hoch | I14: hoch | K14: hoch | M14: hoch | P14: sehr hoch
A15: D | B15: ='12.lan'!D279 -> D - Electric, Gas, Steam and Refrigeration | E15: mittel | I15: mittel | K15: sehr hoch | L15: major impact on climate change | M15: hoch | P15: sehr hoch
A16: E | B16: ='12.lan'!D280 -> E - Water supply, waste management | E16: mittel | I16: hoch | K16: hoch | M16: hoch | P16: mittel
A17: F | B17: ='12.lan'!D281 -> F - Construction industry | E17: sehr hoch | I17: sehr hoch | K17: sehr hoch | L17: major impact on climate change (see d3) and impacting land-use-change | M17: sehr hoch | P17: sehr hoch
A18: G | B18: ='12.lan'!D282 -> G - Wholesale and retail | E18: mittel | I18: sehr hoch | K18: mittel | M18: mittel | P18: hoch
A19: H | B19: ='12.lan'!D283 -> H - Transport and warehousing | E19: mittel | I19: mittel | K19: sehr hoch | M19: mittel | P19: hoch
A20: I | B20: ='12.lan'!D284 -> I - Accommodation and catering | E20: hoch | I20: mittel | K20: hoch | M20: mittel | P20: hoch
A21: J | B21: ='12.lan'!D285 -> J - Information and Communication | E21: mittel | I21: mittel | K21: hoch | M21: mittel | P21: hoch
A22: K | B22: ='12.lan'!D286 -> K - Financial services | E22: mittel | I22: sehr hoch | K22: mittel | M22: mittel | P22: mittel
A23: L | B23: ='12.lan'!D287 -> L - Real estate | E23: mittel | I23: sehr hoch | K23: mittel | M23: mittel | P23: hoch
A24: M | B24: ='12.lan'!D288 -> M - Professional, technical and scientific services | E24: mittel | I24: mittel | K24: mittel | M24: mittel | P24: mittel
A25: N | B25: ='12.lan'!D289 -> N - Administrative and support services | E25: mittel | I25: mittel | K25: mittel | M25: mittel | P25: mittel
A26: O | B26: ='12.lan'!D290 -> O - Public administration; defence; social security | E26: mittel | I26: mittel | K26: mittel | M26: mittel | P26: mittel
A27: P | B27: ='12.lan'!D291 -> P - Education | E27: mittel | I27: mittel | K27: mittel | M27: mittel | P27: mittel
A28: Q | B28: ='12.lan'!D292 -> Q - Health and social work | E28: mittel | I28: mittel | K28: mittel | M28: mittel | P28: mittel
A29: R | B29: ='12.lan'!D293 -> R - Art, education and leisure | E29: mittel | I29: mittel | K29: mittel | M29: mittel | P29: mittel
... A32: U | B32: ='12.lan'!D296 -> U - Extraterritorial organisations and bodies | E32: mittel | I32: mittel | K32: mittel | M32: mittel | P32: mittel
A34: ='9. Weighting'!H35 -> J | B34: Branche 1 | C34: ='9. Weighting'!I35 -> 0.87 | I34: =IFERROR(VLOOKUP(A34,'10. Industry'!$A$4:$O$32,9,FALSE()),"mittel") -> mittel | J34: =VLOOKUP(I34,'9. Weighting'!$F$49:$H$53,3,FALSE()) -> 1 | K34: =IFERROR(VLOOKUP(A34,'10. Industry'!$A$4:$O$32,11,FALSE()),"mittel") -> hoch | L34: =VLOOKUP(K34,'9. Weighting'!$F$49:$H$53,3,FALSE()) -> 1.5
A35: ='9. Weighting'!H36 -> Ce | B35: Branche 2 | C35: ='9. Weighting'!I36 -> 0.13 | I35: =IFERROR(VLOOKUP(A35,'10. Industry'!$A$4:$O$32,9,FALSE()),"mittel") -> hoch | J35: =VLOOKUP(I35,'9. Weighting'!$F$49:$H$53,3,FALSE()) -> 1.5 | K35: =IFERROR(VLOOKUP(A35,'10. Industry'!$A$4:$O$32,11,FALSE()),"mittel") -> hoch | L35: =VLOOKUP(K35,'9. Weighting'!$F$49:$H$53,3,FALSE()) -> 1.5
A36: ='9. Weighting'!H37 -> Pl | B36: Branche 3 | C36: ='9. Weighting'!I37 -> 0 | I36: =IFERROR(VLOOKUP(A36,'10. Industry'!$A$4:$O$32,9,FALSE()),"mittel") -> mittel | J36: =VLOOKUP(I36,'9. Weighting'!$F$49:$H$53,3,FALSE()) -> 1 | K36: =IFERROR(VLOOKUP(A36,'10. Industry'!$A$4:$O$32,11,FALSE()),"mittel") -> mittel | L36: =VLOOKUP(K36,'9. Weighting'!$F$49:$H$53,3,FALSE()) -> 1
C37: =1-SUM(C34:C36) -> 0 | I37: mittel | J37: =VLOOKUP(I37,'9. Weighting'!$F$49:$H$53,3,FALSE()) -> 1 | K37: mittel | L37: =VLOOKUP(K37,'9. Weighting'!$F$49:$H$53,3,FALSE()) -> 1
C38: =SUM(C34:C37) -> 1 | J38: =C34*J34+C35*J35+C36*J36+C37*J37 -> 1.065 | L38: =C34*L34+C35*L35+C36*L36+C37*L37 -> 1.5
B39: ÖKOLOGISCHE BRANCHENGEWICHTUNGEN | J39: =IF(J38<0.75,"niedrig",IF(J38<1.25,"mittel",IF(J38>1.75,"sehr hoch","hoch"))) -> mittel | L39: =IF(L38<0.75,"niedrig",IF(L38<1.25,"mittel",IF(L38>1.75,"sehr hoch","hoch"))) -> hoch

Sheet 11.Region
A1: SUPPLIERS AND EMPLOYEE WEIGHTING RATIO
B2: added value of suppliers (source: income statement) | C2: Splitted added value (source¿?) | D2: Country | E2: PPP index (source¿?) | F2: Added value adjusted | G2: Total | H2: % | I2: ITUC (average) | J2: Industry | K2: nace | L2: ecol. Impact (A3) | O2: social impact (A1)
A3: Supplier 1 | B3: ='9. Weighting'!I10 -> 200000 | C3: ='9. Weighting'!I13 -> 3388 | D3: ='9. Weighting'!H13 -> EGY Ägypten | E3: =IFERROR(VLOOKUP(D3,$A$22:$G$400,3,FALSE()),$C$243) -> 1.0030457 | F3: =IFERROR(C3*E3,"0") -> 3398.3187 | G3: =SUM(F3:F8) -> 200609.13 | H3: =IFERROR(F3/$G$3,"-") -> 0.01694 | I3: =IFERROR(VLOOKUP(D3,$A$21:$I$134,6,FALSE()),2.99) -> 2.99 | J3: ='9. Weighting'!E13 -> A | K3: ='9. Weighting'!G13 -> 0 | L3: =IFERROR(VLOOKUP(J3,'10. Industry'!$A$4:$P$32,16,FALSE()),'3. Calc'!C104) -> sehr hoch | M3: =VLOOKUP(L3,'9. Weighting'!$F$49:$H$53,3,FALSE()) -> 2 | N3: =M3*H3 -> 0.03388 | O3: =IFERROR(VLOOKUP(J3,'10. Industry'!$A$4:$N$32,5,FALSE()),'3. Calc'!C104) -> sehr hoch | P3: =VLOOKUP(O3,'9. Weighting'!$F$49:$H$53,3,FALSE()) -> 2 | Q3: =P3*H3 -> 0.03388
A4: Supplier 2 | C4: ='9. Weighting'!I14 -> 654 | D4: ='9. Weighting'!H14 -> AFG Afghanistan | E4: =IFERROR(VLOOKUP(D4,$A$22:$G$400,3,FALSE()),$C$243) -> 1.0030457 | F4: =IFERROR(C4*E4,"0") -> 655.99187 | H4: =IFERROR(F4/$G$3,"-") -> 0.00327 | I4: =IFERROR(VLOOKUP(D4,$A$21:$I$134,6,FALSE()),2.99) -> 2.99 | J4: ='9. Weighting'!E14 -> Ca | K4: ='9. Weighting'!G14 -> 0 | L4: =IFERROR(VLOOKUP(J4,'10. Industry'!$A$4:$P$32,16,FALSE()),'3. Calc'!C104) -> sehr hoch | M4: =VLOOKUP(L4,'9. Weighting'!$F$49:$H$53,3,FALSE()) -> 2 | N4: =M4*H4 -> 0.00654 | O4: =IFERROR(VLOOKUP(J4,'10. Industry'!$A$4:$N$32,5,FALSE()),'3. Calc'!C104) -> sehr hoch | P4: =VLOOKUP(O4,'9. Weighting'!$F$49:$H$53,3,FALSE()) -> 2 | Q4: =P4*H4 -> 0.00654
A5: Supplier 3 | C5: ='9. Weighting'!I15 -> 456 | D5: ='9. Weighting'!H15 -> DZA Algerien | E5: =IFERROR(VLOOKUP(D5,$A$22:$G$400,3,FALSE()),$C$243) -> 1.0030457 | F5: =IFERROR(C5*E5,"0") -> 457.38882 | H5: =IFERROR(F5/$G$3,"-") -> 0.00228 | I5: =IFERROR(VLOOKUP(D5,$A$21:$I$134,6,FALSE()),2.99) -> 2.99 | J5: ='9. Weighting'!E15 -> A | K5: ='9. Weighting'!G15 -> 0 | L5: =IFERROR(VLOOKUP(J5,'10. Industry'!$A$4:$P$32,16,FALSE()),'3. Calc'!C104) -> sehr hoch | M5: =VLOOKUP(L5,'9. Weighting'!$F$49:$H$53,3,FALSE()) -> 2 | N5: =M5*H5 -> 0.00456 | O5: =IFERROR(VLOOKUP(J5,'10. Industry'!$A$4:$N$32,5,FALSE()),'3. Calc'!C104) -> sehr hoch | P5: =VLOOKUP(O5,'9. Weighting'!$F$49:$H$53,3,FALSE()) -> 2 | Q5: =P5*H5 -> 0.00456
A6: Supplier 4 | C6: ='9. Weighting'!I16 -> 77 | D6: ='9. Weighting'!H16 -> BGD Bangladesch | E6: =IFERROR(VLOOKUP(D6,$A$22:$G$400,3,FALSE()),$C$243) -> 1.0030457 | F6: =IFERROR(C6*E6,"0") -> 77.234516 | H6: =IFERROR(F6/$G$3,"-") -> 0.000385 | I6: =IFERROR(VLOOKUP(D6,$A$21:$I$134,6,FALSE()),2.99) -> 2.99 | J6: ='9. Weighting'!E16 -> A | K6: ='9. Weighting'!G16 -> 0 | L6: =IFERROR(VLOOKUP(J6,'10. Industry'!$A$4:$P$32,16,FALSE()),'3. Calc'!C104) -> sehr hoch | M6: =VLOOKUP(L6,'9. Weighting'!$F$49:$H$53,3,FALSE()) -> 2 | N6: =M6*H6 -> 0.00077 | O6: =IFERROR(VLOOKUP(J6,'10. Industry'!$A$4:$N$32,5,FALSE()),'3. Calc'!C104) -> sehr hoch | P6: =VLOOKUP(O6,'9. Weighting'!$F$49:$H$53,3,FALSE()) -> 2 | Q6: =P6*H6 -> 0.00077
A7: Supplier 5 | C7: ='9. Weighting'!I17 -> 0 | D7: ='9. Weighting'!H17 -> 0 | E7: =IFERROR(VLOOKUP(D7,$A$22:$G$400,3,FALSE()),$C$243) -> 1.0030457 | F7: =IFERROR(C7*E7,"0") -> 0 | H7: =IFERROR(F7/$G$3,"-") -> 0 | I7: =IFERROR(VLOOKUP(D7,$A$21:$I$134,6,FALSE()),2.99) -> 2.99 | J7: ='9. Weighting'!E17 -> Pl | K7: ='9. Weighting'!G17 -> 0 | L7: =IFERROR(VLOOKUP(J7,'10. Industry'!$A$4:$P$32,16,FALSE()),'3. Calc'!C104) -> 1 | M7: =VLOOKUP(L7,'9. Weighting'!$F$49:$H$53,3,FALSE()) -> #N/A | N7: =M7*H7 -> #N/A | O7: =IFERROR(VLOOKUP(J7,'10. Industry'!$A$4:$N$32,5,FALSE()),'3. Calc'!C104) -> 1 | P7: =VLOOKUP(O7,'9. Weighting'!$F$49:$H$53,3,FALSE()) -> #N/A | Q7: =P7*H7 -> #N/A
A8: Rest of suppliers | C8: ='9. Weighting'!I18 -> 195425 | D8: ='9. Weighting'!H18 -> QAT Katar | E8: =IFERROR(VLOOKUP(D8,$A$22:$G$400,3,FALSE()),$C$243) -> 1.0030457 | F8: =IFERROR(C8*E8,"0") -> 196020.2 | H8: =IFERROR(F8/$G$3,"-") -> 0.977125 | I8: =IFERROR(VLOOKUP(D8,$A$21:$I$134,6,FALSE()),2.99) -> 2.99 | J8: Supply Chain Gewichtung | N8: =IFERROR((SUM(N3:N7)*1)/SUM(H3:H7),1) -> 1 | Q8: =IFERROR((SUM(Q3:Q7)*1)/SUM(H3:H7),1) -> 1
I9: =IFERROR(I3*H3+I4*H4+I5*H5+I6*H6+I7*H7+I8*H8,I21) -> 2.99
A10: Workers | B10: ='9. Weighting'!I25 -> 5501 | C10: ='2. Company Facts'!D30 -> 0.46 | D10: ='2. Company Facts'!B30 -> ETH Äthiopien | E10: =IFERROR(VLOOKUP(D10,$A$22:$G$400,3,FALSE()),$C$243) -> 1.0030457 | F10: =C10*E10*B10 -> 2538.1669 | G10: =F10+F11+F12+F13 -> 5517.7542 | H10: =SUM(H3:H8) -> 1 | I10: =IFERROR(VLOOKUP(D10,$A$21:$I$134,6,FALSE()),I28) -> 0
C11: ='2. Company Facts'!D31 -> 0.11 | D11: ='2. Company Facts'!B31 -> BHR Bahrain | E11: =IFERROR(VLOOKUP(D11,$A$22:$G$400,3,FALSE()),$C$243) -> 1.0030457 | F11: =C11*E11*B10 -> 606.95296 | I11: =IFERROR(VLOOKUP(D11,$A$21:$I$134,6,FALSE()),I29) -> 0
C12: ='2. Company Facts'!D32 -> 0 | D12: ='2. Company Facts'!B32 -> 0 | E12: =IFERROR(VLOOKUP(D12,$A$22:$G$400,3,FALSE()),$C$243) -> 1.0030457 | F12: =C12*E12*B10 -> 0 | I12: =IFERROR(VLOOKUP(D12,$A$21:$I$134,6,FALSE()),I30) -> 0
C13: =1-C10-C11-C12 -> 0.43 | D13: =A21 -> Country Code | E13: =IFERROR(VLOOKUP(D13,$A$22:$G$400,3,FALSE()),$C$243) -> 1.0030457 | F13: =C13*E13*B10 -> 2372.6343 | I13: =IFERROR(VLOOKUP(D13,$A$21:$I$134,9,FALSE()),"0") -> 0
A14: Please note that the boxes with a red frame have to be filled out. | I14: =I10*C10+I11*C11+I12*C12+I13*C13 -> 0
A17: Purchasing Power Parity Tables
A18: Data Source | B18: Worldbank Data
A19: Last Updated Date | B19: 2_2018 | E19: http://data.worldbank.org/indicator/NY.GDP.MKTP.PP.CD
A21: Country Code | B21: Country Name | C21: PPP Factor | E21: Region | F21: ITUC | J21: code
A22: ='12.lan'!D339 -> ABW Aruba | B22: Aruba | C22: 1.539377 | D22: 2017 | E22: Americas | F22: 3.52 | G22: est | J22: ABW
A23: ='12.lan'!D340 -> AFG Afghanistan | B23: Afghanistan | C23: 3.4673949 | D23: - | E23: Asia | F23: 5 | G23: est | J23: AFG
A24: ='12.lan'!D341 -> AGO Angola | B24: Angola | C24: 1.9978684 | D24: - | E24: Africa | F24: 4 | J24: AGO
A25: ='12.lan'!D342 -> ALB Albania | B25: Albania | C25: 2.6310494 | D25: - | E25: Europe | F25: 3 | J25: ALB
A26: ='12.lan'!D343 -> AND Andorra | B26: Andorra | C26: 1.0331403 | D26: est | E26: Europe | F26: 2.55 | G26: est | J26: AND
A27: ='12.lan'!D344 -> ARE United Arab Emirates | B27: United Arab Emirates | C27: 1.840872 | D27: - | E27: Asia | F27: 5 | J27: ARE
A28: ='12.lan'!D345 -> ARG Argentina | B28: Argentina | C28: 2.0521283 | D28: - | E28: Americas | F28: 4 | J28: ARG
A29: ='12.lan'!D346 -> ARM Armenia | B29: Armenia | C29: 2.3471442 | D29: - | E29: Asia | F29: 4.47 | G29: est | J29: ARM
A30: ='12.lan'!D347 -> ASM American Samoa | B30: American Samoa | C30: 1.4985869 | D30: est | E30: Oceania | F30: 4.05 | J30: ASM
A31: ='12.lan'!D348 -> ATG Antigua and Barbuda | B31: Antigua and Barbuda | C31: 1.7752454 | D31: - | E31: Americas | F31: 3.52 | G31: est | J31: ATG
A32: ='12.lan'!D349 -> AUS Australia | B32: Australia | C32: 0.90888933 | D32: - | E32: Oceania | F32: 3 | G32: est | J32: AUS
A33: ='12.lan'!D350 -> AUT Austria | B33: Austria | C33: 1.1086532 | D33: - | E33: Europe | F33: 1 | J33: AUT
A34: ='12.lan'!D351 -> AZE Azerbaijan | B34: Azerbaijan | C34: 3.1277796 | D34: - | E34: Asia | F34: 4.47 | G34: est | J34: AZE
A35: ='12.lan'!D352 -> BDI Burundi | B35: Burundi | C35: 3.5302047 | D35: - | E35: Africa | F35: 6 | G35: est | J35: BDI
A36: ='12.lan'!D353 -> BEL Belgium | B36: Belgium | C36: 1.0899264 | D36: - | E36: Europe | F36: 2 | J36: BEL
A37: ='12.lan'!D354 -> BEN Benin | B37: Benin | C37: 2.7025849 | D37: - | E37: Africa | F37: 4 | G37: est | J37: BEN
A38: ='12.lan'!D355 -> BFA Burkina Faso | B38: Burkina Faso | C38: 2.7876176 | D38: - | E38: Africa | F38: 3 | G38: est | J38: BFA
A39: ='12.lan'!D356 -> BGD Bangladesh | B39: Bangladesh | C39: 3.6333909 | D39: - | E39: Asia | F39: 5 | J39: BGD
A40: ='12.lan'!D357 -> BGR Bulgaria | B40: Bulgaria | C40: 2.5384498 | D40: - | E40: Europe | F40: 3 | J40: BGR
A41: ='12.lan'!D358 -> BHR Bahrain | B41: Bahrain | C41: 2.2064625 | D41: - | E41: Asia | F41: 5 | J41: BHR
A42: ='12.lan'!D359 -> BHS Bahamas | B42: Bahamas, The | C42: 1.1770469 | D42: - | E42: Americas | F42: 3 | G42: est | J42: BHS
A43: ='12.lan'!D360 -> BIH Bosnia and Herzegovina | B43: Bosnia and Herzegovina | C43: 2.4242502 | D43: - | E43: Europe | F43: 4 | J43: BIH
A44: ='12.lan'!D361 -> BLR Belarus | B44: Belarus | C44: 2.9646094 | D44: - | E44: Europe | F44: 5 | J44: BLR
A45: ='12.lan'!D362 -> BLZ Belize | B45: Belize | C45: 2.0353238 | D45: - | E45: Americas | F45: 3 | G45: est | J45: BLZ
A46: ='12.lan'!D363 -> BMU Bermuda | B46: Bermuda | C46: 1.0030457 | D46: est | E46: Americas | F46: 3.52 | G46: est | J46: BMU
A47: ='12.lan'!D364 -> BOL Bolivia, Plurinational State of | B47: Bolivia | C47: 3.0760428 | D47: - | E47: Americas | F47: 3 | J47: BOL
A48: ='12.lan'!D365 -> BRA Brazil | B48: Brazil | C48: 1.4598267 | D48: - | E48: Americas | F48: 5 | J48: BRA
A49: ='12.lan'!D366 -> BRB Barbados | B49: Barbados | C49: 1.158327 | D49: - | E49: Americas | F49: 2 | G49: est | J49: BRB
A50: ='12.lan'!D367 -> BRN Brunei Darussalam | B50: Brunei Darussalam | C50: 2.5740493 | D50: - | E50: Asia | F50: 4.47 | G50: est | J50: BRN
A51: ='12.lan'!D368 -> BTN Bhutan | B51: Bhutan | C51: 3.2506174 | D51: - | E51: Asia | F51: 4.47 | G51: est | J51: BTN
A52: ='12.lan'!D369 -> BWA Botswana | B52: Botswana | C52: 2.317988 | D52: - | E52: Africa | F52: 4 | J52: BWA
A53: ='12.lan'!D370 -> CAF Central African Republic | B53: Central African Republic | C53: 2.2689877 | D53: - | E53: Africa | F53: 6 | G53: est | J53: CAF
A54: ='12.lan'!D371 -> CAN Canada | B54: Canada | C54: 0.93653738 | D54: - | E54: Americas | F54: 3 | J54: CAN
A55: ='12.lan'!D372 -> CHE Switzerland | B55: Switzerland | C55: 0.85919959 | D55: - | E55: Europe | F55: 2 | G55: est | J55: CHE
A56: ='12.lan'!D373 -> CHL Chile | B56: Chile | C56: 1.667037 | D56: - | E56: Americas | F56: 4 | J56: CHL
A57: ='12.lan'!D374 -> CHN China | B57: China | C57: 2.3523345 | D57: - | E57: Asia | F57: 5 | J57: CHN
A58: ='12.lan'!D375 -> CIV Côte d'Ivoire | B58: Cote d'Ivoire | C58: 2.485658 | D58: - | E58: Africa | F58: 4 | J58: CIV
A59: ='12.lan'!D376 -> CMR Cameroon | B59: Cameroon | C59: 2.5222031 | D59: - | E59: Africa | F59: 4 | J59: CMR
A60: ='12.lan'!D377 -> COD Congo, the Democratic Republic of the | B60: Congo, Dem. Rep. | C60: 2.2261429 | D60: - | E60: Africa | F60: 2 | J60: COD
A61: ='12.lan'!D378 -> COG Congo | B61: Congo, Rep. | C61: 2.1352573 | D61: - | E61: Africa | F61: 3.79 | J61: COG
A62: ='12.lan'!D379 -> COL Colombia | B62: Colombia | C62: 1.9518236 | D62: - | E62: Americas | F62: 5 | J62: COL
A63: ='12.lan'!D380 -> COM Comoros | B63: Comoros | C63: 2.0789533 | D63: - | E63: Africa | F63: 3.79 | G63: est | J63: COM
A64: ='12.lan'!D381 -> CPV Cape Verde | B64: Cabo Verde | C64: 1.9826994 | D64: - | E64: Africa | F64: 3.79 | G64: est | J64: CPV
A65: ='12.lan'!D382 -> CRI Costa Rica | B65: Costa Rica | C65: 1.7868103 | D65: - | E65: Americas | F65: 2 | J65: CRI
A66: ='12.lan'!D383 -> CUB Cuba | B66: Cuba | C66: 1.8343461 | D66: est | E66: Americas | F66: 3.52 | G66: est | J66: CUB
A67: ='12.lan'!D384 -> CUW Curaçao | B67: Curacao | C67: 1.8343461 | D67: est | E67: Americas | F67: 3.52 | G67: est | J67: CUW
A68: ='12.lan'!D385 -> CYM Cayman Islands | B68: Cayman Islands | C68: 0.89501403 | D68: 2017 | E68: Americas | F68: 3.52 | G68: est | J68: CYM
A69: ='12.lan'!D386 -> CYP Cyprus | B69: Cyprus | C69: 1.222334 | D69: - | E69: Asia | F69: 4.47 | G69: est | J69: CYP
A70: ='12.lan'!D387 -> CZE Czech Republic | B70: Czech Republic | C70: 1.7014347 | D70: - | E70: Europe | F70: 2 | J70: CZE
A71: ='12.lan'!D388 -> DEU Germany | B71: Germany | C71: 1.1178803 | D71: - | E71: Europe | F71: 1 | J71: DEU
A72: ='12.lan'!D389 -> DJI Djibouti | B72: Djibouti | C72: 2.5145504 | D72: est | E72: Africa | F72: 4 | G72: est | J72: DJI
A73: ='12.lan'!D390 -> DMA Dominica | B73: Dominica | C73: 1.6625762 | D73: - | E73: Americas | F73: 2 | G73: est | J73: DMA
A74: ='12.lan'!D391 -> DNK Denmark | B74: Denmark | C74: 0.87158519 | D74: - | E74: Europe | F74: 1 | J74: DNK
A75: ='12.lan'!D392 -> DOM Dominican Republic | B75: Dominican Republic | C75: 2.3056408 | D75: - | E75: Americas | F75: 2 | J75: DOM
A76: ='12.lan'!D393 -> DZA Algeria | B76: Algeria | C76: 3.2494893 | D76: - | E76: Africa | F76: 5 | J76: DZA
A77: ='12.lan'!D394 -> ECU Ecuador | B77: Ecuador | C77: 2.2631013 | D77: - | E77: Americas | F77: 5 | J77: ECU
A78: ='12.lan'!D395 -> EGY Egypt | B78: Egypt, Arab Rep. | C78: 4.2693339 | D78: - | E78: Africa | F78: 5 | J78: EGY
A79: ='12.lan'!D396 -> ERI Eritrea | B79: Eritrea | C79: 2.5145504 | D79: est | E79: Africa | F79: 5 | G79: est | J79: ERI
A80: ='12.lan'!D397 -> ESP Spain | B80: Spain | C80: 1.2053397 | D80: - | E80: Europe | F80: 3 | J80: ESP
A81: ='12.lan'!D398 -> EST Estonia | B81: Estonia | C81: 1.8028236 | D81: - | E81: Europe | F81: 2 | J81: EST
A82: ='12.lan'!D399 -> ETH Ethiopia | B82: Ethiopia | C82: 3.545709 | D82: - | E82: Africa | F82: 4 | J82: ETH
A83: ='12.lan'!D400 -> FIN Finland | B83: Finland | C83: 0.9931866 | D83: - | E83: Europe | F83: 1 | J83: FIN
A84: ='12.lan'!D401 -> FJI Fiji | B84: Fiji | C84: 2.2688294 | D84: - | E84: Oceania | F84: 4 | G84: est | J84: FJI
A85: ='12.lan'!D402 -> FRA France | B85: France | C85: 1.0384488 | D85: - | E85: Europe | F85: 2 | J85: FRA
A86: ='12.lan'!D403 -> FRO Faroe Islands | B86: Faroe Islands | C86: 1.0331403 | D86: est | E86: Europe | F86: 2.55 | G86: est | J86: FRO
A87: ='12.lan'!D404 -> FSM Micronesia, Federated States of | B87: Micronesia, Fed. Sts. | C87: 1.3021436 | D87: - | E87: Oceania | F87: 4.05 | G87: est | J87: FSM
A88: ='12.lan'!D405 -> GAB Gabon | B88: Gabon | C88: 1.9768693 | D88: - | E88: Africa | F88: 3.79 | G88: est | J88: GAB
A89: ='12.lan'!D406 -> GBR United Kingdom | B89: United Kingdom | C89: 1.0611427 | D89: - | E89: Europe | F89: 3 | J89: GBR
A90: ='12.lan'!D407 -> GEO Georgia | B90: Georgia | C90: 2.5426401 | D90: - | E90: Asia | F90: 3 | J90: GEO
A91: ='12.lan'!D408 -> GHA Ghana | B91: Ghana | C91: 2.6267394 | D91: - | E91: Africa | F91: 3 | J91: GHA
A92: ='12.lan'!D409 -> GIB Gibraltar | B92: Gibraltar | C92: 1.0331403 | D92: est | E92: Europe | F92: 2.55 | G92: est | J92: GIB
A93: ='12.lan'!D410 -> GIN Guinea | B93: Guinea | C93: 2.7930324 | D93: - | E93: Africa | F93: 3.79 | G93: est | J93: GIN
A94: ='12.lan'!D411 -> GMB Gambia | B94: Gambia, The | C94: 3.3215792 | D94: - | E94: Africa | F94: 3.79 | G94: est | J94: GMB
A95: ='12.lan'!D412 -> GNB Guinea-Bissau | B95: Guinea-Bissau | C95: 2.892021 | D95: - | E95: Africa | F95: 3.79 | G95: est | J95: GNB
A96: ='12.lan'!D413 -> GNQ Equatorial Guinea | B96: Equatorial Guinea | C96: 2.2178293 | D96: - | E96: Africa | F96: 3.79 | G96: est | J96: GNQ
A97: ='12.lan'!D414 -> GRC Greece | B97: Greece | C97: 1.2561358 | D97: - | E97: Europe | F97: 5 | J97: GRC
A98: ='12.lan'!D415 -> GRD Grenada | B98: Grenada | C98: 1.7103101 | D98: - | E98: Americas | F98: 3.52 | G98: est | J98: GRD
A99: ='12.lan'!D416 -> GRL Greenland | B99: Greenland | C99: 1.0030457 | D99: est | E99: Americas | F99: 3.52 | G99: est | J99: GRL
A100: ='12.lan'!D417 -> GTM Guatemala | B100: Guatemala | C100: 2.677994 | D100: - | E100: Americas | F100: 5 | J100: GTM
A101: ='12.lan'!D418 -> GUM Guam | B101: Guam | C101: 1.4985869 | D101: est | E101: Oceania | F101: 4.05 | G101: est | J101: GUM
A102: ='12.lan'!D419 -> GUY Guyana | B102: Guyana | C102: 2.1643907 | D102: - | E102: Americas | F102: 3.52 | G102: est | J102: GUY
A103: ='12.lan'!D420 -> HKG Hong Kong | B103: Hong Kong SAR, China | C103: 1.6656418 | D103: - | E103: Asia | F103: 5 | J103: HKG
...

Sheet 12.lan
C1: =VLOOKUP('0. Intro'!B1,'12.lan'!B2:C12,2,FALSE()) -> 3 | D1: =HLOOKUP($C$1,$E$1:$V$4910,ROW(D1)) -> 3 | E1: 1 | F1: 2 | G1: 3 | H1: 4 | I1: 5
A2: 3 | B2: Select your language | C2: =A2 -> 3 | D2: =HLOOKUP($C$1,$E$1:$V$4910,ROW(D2)) -> English | E2: Deutsch | F2: Italiano | G2: English | H2: Español | I2: Francais
A3: 1 | B3: Deutsch | C3: =A3 -> 1 | D3: =HLOOKUP($C$1,$E$1:$V$4910,ROW(D3)) -> 0
A4: 2 | B4: Italiano | C4: =A4 -> 2 | D4: =HLOOKUP($C$1,$E$1:$V$4910,ROW(D4)) -> BALANCE SHEET CALCULATOR | E4: GEMEINWOHL-RECHNER | F4: Calcolatore del Bene Comune | G4: BALANCE SHEET CALCULATOR | H4: CALCULADORA DEL BIEN COMÚN | I4: Calculateur du Bilan pour le Bien Commun
A5: 3 | B5: English | C5: =A5 -> 3 | D5: =HLOOKUP($C$1,$E$1:$V$4910,ROW(D5)) -> © ECG | E5: © GWÖ | F5: © Economia del Bene Comune | G5: © ECG | H5: © Economía del Bien Común | I5: © Economie pour le Bien Commun
A6: 4 | B6: Español | C6: =A6 -> 4 | D6: =HLOOKUP($C$1,$E$1:$V$4910,ROW(D6)) -> Version | E6: Version | F6: Versione | G6: Version | H6: Versión | I6: Version
A7: 5 | B7: Francais | C7: =A7 -> 5 | D7: =HLOOKUP($C$1,$E$1:$V$4910,ROW(D7)) -> WELCOME! | E7: HERZLICH WILLKOMMEN! | F7: Benvenuto! | G7: WELCOME! | H7: ¡Bienvenid@! | I7: Bienvenue!
A8: 6 | C8: =A8 -> 6 | D8: =HLOOKUP($C$1,$E$1:$V$4910,ROW(D8)) -> This tool is for calculating the overall Common Good Points for your company or organisation. It complements the Common Good Report and has to be used together with it. Have fun with your calculation! | E8: Dieses Tool dient zur Berechnung der Gemeinwohl-Punkte Ihres Unternehmens. Es ist eine Ergänzung zum Gemeinwohlbericht und muss gemeinsam mit diesem genutzt werden. Wir wünschen gutes Gelingen! | F8: Può utilizzare questo strumento per calcolare i punti del bene comune della sua impresa. Serve quale completamento alla relazione del bene comune e deve essere utilizzato assieme a questo. Le auguriamo buon divertimento in questa attività di calcolo! | G8: This tool is for calculating the overall Common Good Points for your company or organisation. It complements the Common Good Report and has to be used together with it. Have fun with your calculation! | H8: Esta herramienta sirve para calcular la puntuación de su empresa de acuerdo al balance del Bien Común. Esta hoja de cálculo es complementaria al informe del Bien Común y debe utilizarse por tanto conjuntamente. ¡Buena suerte! | I8: Cet outil sert à calculer le total des points de l'EBC pour votre entreprise ou organisation. Il complète le rapport de l'Economie pour le Bien Commun et doit être utiliser en lien avec le rapport. Bonne chance pour vos calculs !
A9: 7 | C9: =A9 -> 7 | D9: =HLOOKUP($C$1,$E$1:$V$4910,ROW(D9)) -> HOW TO USE THE BALANCE SHEET CALCULATOR: | E9: WIE SIE DEN BILANZ-RECHNER RICHTIG VERWENDEN: | F9: Come utilizzare correttamente il calcolatore del bilancio: | G9: HOW TO USE THE BALANCE SHEET CALCULATOR: | H9: Cómo utilizar la calculadora del Bien Común correctamente | I9: Comment utiliser le calculateur du bilan :
A10: 8 | C10: =A10 -> 8 | D10: =HLOOKUP($C$1,$E$1:$V$4910,ROW(D10)) -> 1. General | E10: 1. Allgemeines | F10: 1. Generale | G10: 1. General | H10: 1. General | I10: 1. Généralités
A11: 9 | C11: =A11 -> 9 | D11: =HLOOKUP($C$1,$E$1:$V$4910,ROW(D11)) -> You can enter general information about your company or organisation in this section. | E11: Hier können Sie allgemeinen Angaben zu Ihrem Unternehmen machen. | F11: Qui può indicare tutte le informazioni e dati della sua impresa | G11: You can enter general information about your company or organisation in this section. | H11: En esta hoja puedes introducir información general sobre tu organización o empresa | I11: Vous pouvez renseigner des informations globales et générales sur votre entreprise ou organisation dans cette rubrique.
A12: 10 | C12: =A12 -> 10 | D12: =HLOOKUP($C$1,$E$1:$V$4910,ROW(D12)) -> All fields in this section must be completed as they are essential for the weighting of each theme. | E12: Hier müssen alle geforderten Kenngrößen eingetragen werden, da diese für die Gewichtung der Themen essentiell sind. | F12: Qui devono essere inseriti tutti i parametri richiesti, poiché questi sono essenziali per la ponderazione degli argomenti. | G12: All fields in this section must be completed as they are essential for the weighting of each theme. | H12: En esta hoja debes introducir todos los datos requeridos, pues el cálculo de la ponderación depende de ellos | I12: Tous les champs dans cette rubrique, doivent être complétés, car ils sont essentiels pour la pondération de chaque sujet.
A13: 11 | D13: =HLOOKUP($C$1,$E$1:$V$4910,ROW(D13)) -> For each theme (A1, B1, ...) a certain maximum number of Common Good Points can be achieved. To evaluate how many points your company scores, follow these steps: | E13: Für jedes Thema (A1, B1, ...) kann eine bestimmte Anzahl an Gemeinwohl-Punkten erreicht werden. Um zu ermitteln, wie viele davon Ihr Unternehmen erhält, gehen Sie wie folgt vor: | F13: Per ogni tema (A1, B1, ...) può essere raggiunto un determinate valore di punteggio del bene comune. Per ricavare, che punteggio ottiene la Sua impresa proceda nel modo seguente: | G13: For each theme (A1, B1, ...) a certain maximum number of Common Good Points can be achieved. To evaluate how many points your company scores, follow these steps: | H13: Para cada tema (A1, B1, …) puede obtenerse una puntuación determinada. Para calcular cuál obtiene su empresa, siga los pasos siguientes: | I13: Pour chaque thème (A1, B1, …) un nombre maximum de Points pour le Bien Commun peuvent être atteints. Pour évaluer combien de points votre entreprise a cumulé, suivez ces étapes :
A14: 12 | D14: =HLOOKUP($C$1,$E$1:$V$4910,ROW(D14)) -> Describe the current status and potential for improvement for the various aspects under key headings. Use the workbook as a reference. (This is optional and not absolutely necessary for the calculation.) | E14: Beschreiben Sie auf Basis des Arbeitsbuchs in wenigen Stichworten Ist-Zustand und Verbesserungspotenzial für die verschiedenen Aspekte (optional, ist für die Berechnung nicht unbedingt notwendig). | F14: Descrivi sulla base del libro di esercizi in poche parole chiave lo stato attuale e il potenziale di miglioramento per i diversi aspetti (facoltativo, non è assolutamente necessario per il calcolo). | G14: Describe the current status and potential for improvement for the various aspects under key headings. Use the workbook as a reference. (This is optional and not absolutely necessary for the calculation.) | H14: Describa en pocas palabras, de acuerdo al manual del Balance del Bien Común, cuál es el estado actual y el potencial de mejora para cada uno de los aspectos (opcional, no es necesario para el cálculo de la puntuación). | I14: Décrivez la situation actuelle et les évolutions potentielles pour améliorer les différents aspects des rubriques clés. Utilisez le guide de l'EBC comme référence. (Ceci est optionnel et pas indispensable pour le calcul.)
A15: 13 | D15: =HLOOKUP($C$1,$E$1:$V$4910,ROW(D15)) -> Based on these descriptions, indicate on a scale of 0-10 how far you consider the respective aspect is met (Achievement level). The criteria for choosing the correct value can be found in the Workbook. | E15: Geben Sie - aufbauend auf diesen Beschreibungen - an, entsprechend welchem Skalenwert (0-10) Ihrer Meinung nach der jeweilige Aspekt erfüllt ist (Spalte "Erfüllungsgrad"). Anhaltspunkte zur Wahl des "richtigen" Skalenwerts finden Sie wiederum im Arbeitsbuch. | F15: In base a queste descrizioni, indica in base a quale valore di scala (0-10) pensi che il rispettivo aspetto sia soddisfatto (colonna "grado di realizzazione"). Troverete indizi per scegliere il valore di scala "corretto" nella cartella di lavoro. | G15: Based on these descriptions, indicate on a scale of 0-10 how far you consider the respective aspect is met (Achievement level). The criteria for choosing the correct value can be found in the Workbook. | H15: A partir de las descripciones previas, introduzca una puntuación de 0 a 10 que indique, según su opinión, el nivel de satisfacción de cada aspecto. Los niveles de referencia para la puntuación y otras indicaciones al respecto se encuentran en el manual. | I15: Basé sur ces descriptions, indiquez sur une échelle de 0 à 10, comment vous pensez avoir atteint les différents critères (niveau de réalisation). Le critère pour choisir la valeur correcte peut être trouvé dans le Guide.
A16: 14 | D16: =HLOOKUP($C$1,$E$1:$V$4910,ROW(D16)) -> Negative aspects are allocated negative points according to the descriptions set out in the Workbook. | E16: Für die Bewertung der Negativaspekte geben Sie Punktewerte entsprechend der Beschreibungen im Arbeitsbuch an. | F16: Per la valutazione degli aspetti negativi si indicano i valori dei punti in base alle descrizioni nel manuale. | G16: Negative aspects are allocated negative points according to the descriptions set out in the Workbook. | H16: Para aportar una puntuación a cada uno de los aspectos negativos utilice las indicaciones del manual. | I16: Les aspects négatifs donnent droit à des points négatifs, selon la description indiquée dans le Guide.
A17: 15 | D17: =HLOOKUP($C$1,$E$1:$V$4910,ROW(D17)) -> Where deemed necessary for your company and in agreement with the auditors you can change the relative weightings of individual aspects (A1.1, A1.2, ..). In the column Weighting, you can select values for each aspect. The distribution of available points for individual aspects will then be adjusted automatically, so that the total of all aspects of an indicator result in 100%. | E17: Sie können, wenn es für ihr Unternehmen notwendig erscheint, in Abstimmung mit der AuditorIn die relativen Gewichtungen der einzelnen Aspekte (A1.1, A1.2, ...) verändern. In der Spalte "Gewichtung" ("Gew.") können Sie für jeden Aspekt Werte auswählen. Die Verteilung der möglichen Punkte auf die einzelnen Aspekte wird dann automatisch angepasst, sodass die Summe aller Aspekte eines Themas immer 100% ergibt. | F17: È possibile modificare le ponderazioni relative dei singoli aspetti (A1.1, A1.2, ...), se necessario per la propria azienda, in consultazione con l’auitor. Nella colonna "Peso", è possibile selezionare i valori per ogni aspetto. La distribuzione dei possibili punti sui singoli aspetti viene quindi regolata automaticamente, in modo che la somma di tutti gli aspetti di un argomento sia sempre al 100%. | G17: Where deemed necessary for your company and in agreement with the auditors you can change the relative weightings of individual aspects (A1.1, A1.2, ..). In the column Weighting, you can select values for each aspect. The distribution of available points for individual aspects will then be adjusted automatically, so that the total of all aspects of an indicator result in 100%. | H17: Puede cambiar las ponderaciones que realiza la hoja de cálculo por defecto, siempre y cuando la auditoría esté de acuerdo. En la columna “Ponderación” puede seleccionar una opción del catálogo. La distribución de los puntos de cada uno de los aspectos se realiza automáticamente, de tal manera que la suma de todos los aspectos del tema siempre tiene como resultado el 100%. | I17: Lorsque cela est jugé nécessaire pour votre entreprise et en accord avec les vérificateurs, vous pouvez modifier la pondération relative des aspects individuels (A1.1, A1.2, …). Dans la colonne pondération, vous pouvez sélectionner des valeurs pour chaque aspect. La distribution des points disponibles pour les aspects individuels, seront ensuite ajustés automatiquement, ainsi le total de tous les aspects d'un indicateur donnera 100%.
A18: 16 | D18: =HLOOKUP($C$1,$E$1:$V$4910,ROW(D18)) -> The calculation automatically weights each theme’s total value against the data in the ‘Company details’ section and rounds it to a whole-number multiple of 10%. | E18: Bei der Berechnung werden die Gesamtwerte pro Thema automatisch entsprechend der Angaben im Faktenblatt gewichtet und auf ganzzahlige Vielfache von 10% gerundet. | F18: Nel calcolo, i totali per argomento vengono automaticamente ponderati in base alla scheda informativa e arrotondati ai multipli interi del 10%. | G18: The calculation automatically weights each theme’s total value against the data in the ‘Company details’ section and rounds it to a whole-number multiple of 10%. | H18: Los valores introducidos son ponderados de acuerdo a los datos introducidos en la hoja 2. Company Facts. El resultado es redondeado y presentado como número entero. | I18: Le calcul pondère automatiquement chaque total de chaque thème comparé aux données contenues dans la rubrique : "les détails de l'entreprise" et l'arrondit à un multiple entier de 10%.
D19: =HLOOKUP($C$1,$E$1:$V$4910,ROW(D19)) -> The ECG-Matrix displays your result in a table. | E19: Die "GW-Matrix" bietet einen tabellarischen Überblick über Ihr Ergebnis. | F19: La "matrice EBC" fornisce una panoramica tabellare del risultato. | G19: The ECG-Matrix displays your result in a table. | H19: La hoja “ECG-Matrix” muestra los resultados en una tabla resumen. | I19: La matrice EBC propose vos résultats sous forme de tableau
D20: =HLOOKUP($C$1,$E$1:$V$4910,ROW(D20)) -> The ECG Matrix displays your result in a table. | E20: Die "GW-Matrix" bietet einen tabellarischen Blick auf Ihr Ergebnis. | F20: La "matrice EBC" offre una vista tabellare del risultato. | G20: The ECG Matrix displays your result in a table. | H20: La hoja “ECG-Matrix” muestra los resultados de la puntuación presentando una vista general en forma de matriz (tabla). | I20: La matrice EBC propose vos résultats sous forme de tableau
D21: =HLOOKUP($C$1,$E$1:$V$4910,ROW(D21)) -> The values-star displays your result arranged by value as a graphic. | E21: Der "Werte-Stern" zeigt schließlich Ihr Ergebnis nach Werten gegliedert in graphischer Form. | F21: La "stella dei valori" mostra infine il risultato in base a valori strutturati in forma grafica. | G21: The values-star displays your result arranged by value as a graphic. | H21: La hoja “Values” muestra un diagrama de araña en el que se muestran las puntuaciones según “valor” o columna de la matriz. | I21: L'étoile des valeurs affiche vos résultats en les disposant par valeur comme un graphique.
D22: =HLOOKUP($C$1,$E$1:$V$4910,ROW(D22)) -> The group-star displays your result arranged by stakeholder as a graphic. | E22: Der "Gruppen-Stern" zeigt schließlich Ihr Ergebnis nach Berührungsgruppen gegliedert in graphischer Form. | F22: La "stella dei gruppi" mostra infine il risultato in base a gruppi d’interesse strutturati in forma grafica. | G22: The group-star displays your result arranged by stakeholder as a graphic. | H22: La hoja “Stakeholders” muestra un diagrama de araña en el que se muestran las puntuaciones según “grupo de interés” o fila de la matriz. | I22: L' étoile groupe affiche vos résultats en les disposant par partie prenante comme un graphique.
D23: =HLOOKUP($C$1,$E$1:$V$4910,ROW(D23)) -> The theme-star displays the result of your themes as a graphic. | E23: Der "Themen-Stern" zeigt schließlich Ihr Ergebnis in allen Themen in graphischer Form. | F23: La "stella dei temi" mostra finalmente il risultato in tutti i temi in forma grafica. | G23: The theme-star displays the result of your themes as a graphic. | H23: La hoja “Topics” muestra un diagrama de araña en el que se muestran las puntuaciones de cada tema. | I23: L'étoile des thèmes affiche les résultats de vos rubriques comme un graphique.
D24: =HLOOKUP($C$1,$E$1:$V$4910,ROW(D24)) -> This is a description of the weighting model. | E24: Hier finden Sie eine Beschreibung der Gewichtungsmodelles. | F24: Qui potete trovare una descrizione del modello di ponderazione. | G24: This is a description of the weighting model. | H24: En la hoja “Descr. Weighting” se encuentra una descripción del método de ponderación. | I24: Ceci est une description du modèle de pondération
D25: =HLOOKUP($C$1,$E$1:$V$4910,ROW(D25)) -> This is where the calculation determines how the individual stakeholder groups and themes are weighted. | E25: Hier erfolgt die Berechnung wie die einzelnen Berührungsgruppen und Themen gewichtet werden. | F25: Qui il calcolo avviene come vengono pesati i singoli gruppi d’interesse ed i temi. | G25: This is where the calculation determines how the individual stakeholder groups and themes are weighted. | H25: En la hoja “Weighting” se realiza el cálculo para las ponderaciones de los grupos de interés y temas. | I25: Ceci montre la méthode de calcul qui détermine comment les thèmes et parties prenantes sont pondérés.
D26: =HLOOKUP($C$1,$E$1:$V$4910,ROW(D26)) -> This contains an assessment of the relevance of supply chains and environmental sustainability for all industry sectors, used in the weighting. | E26: Enthält Einschätzungen der Relevanz von Zulieferkette und ökologische Nachhaltigkeit für alle Branchen,, die für die Gewichtung herangezogen werden. | F26: Include stime della dell'importanza della rete dei fornitori e della sostenibilità ambientale per tutti i settori utilizzati per la ponderazione. | G26: This contains an assessment of the relevance of supply chains and environmental sustainability for all industry sectors, used in the weighting. | H26: Esta hoja contiene estimaciones sobre la relevancia de la cadena de suministro y sostenibilidad medioambiental de todos los sectores. Esta información se utiliza para realizar la ponderación. | I26: Il s’agit d’une évaluation de la pertinence des chaînes d’approvisionnement et de la durabilité environnementale pour tous les secteurs industriels, utilisés dans la pondération.
D27: =HLOOKUP($C$1,$E$1:$V$4910,ROW(D27)) -> This contains statistics for countries and regions used in the weighting. | E27: Enthält Statistiken für Länder und Regionen, die für die Gewichtung herangezogen werden. | F27: Contiene statistiche per paesi e regioni utilizzati per la ponderazione. | G27: This contains statistics for countries and regions used in the weighting. | H27: Esta hoja contiene estadísticas de países y regiones que son utilizadas para realizar las ponderaciones. | I27: Il contient des statistiques pour les pays et régions utilisés dans la pondération.
D28: =HLOOKUP($C$1,$E$1:$V$4910,ROW(D28)) -> 2. Company details | E28: 2. Fakten zum Unternehmen | F28: 2. Fatti sull'impresa | G28: 2. Company details | H28: 2. Datos de la empresa | I28: 2. Détails de l'entreprise
D29: =HLOOKUP($C$1,$E$1:$V$4910,ROW(D29)) -> 3. Scoring | E29: 3. Berechnung | F29: 3. calcolo | G29: 3. Scoring | H29: 3. Cálculo | I29: 3. Score
D30: =HLOOKUP($C$1,$E$1:$V$4910,ROW(D30)) -> 4. ECG Matrix | E30: 4. GW-Matrix | F30: 4. matrice del bene comune | G30: 4. ECG Matrix | H30: 4. Matriz EBC | I30: 4. Matrice de l'EBC
... D37: =HLOOKUP($C$1,$E$1:$V$4910,ROW(D37)) -> 11. Countries (hidden) | E37: 11. Länder und Regionen (ausgeblendet) | F37: 11. Paesi e regioni (nascosti) | G37: 11. Countries (hidden) | H37: 11. Países y regiones (oculta) | I37: 11. Pays et régions(caché)
I38: 0
D39: =HLOOKUP($C$1,$E$1:$V$4910,ROW(D39)) -> 0 | I39: 0
D40: =HLOOKUP($C$1,$E$1:$V$4910,ROW(D40)) -> KEY | E40: LEGENDE | F40: LEGENDA | G40: KEY | H40: LEYENDA | I40: LEGENDE
D41: =HLOOKUP($C$1,$E$1:$V$4910,ROW(D41)) -> Field is editable (green frame, dark green text) | E41: Feld ist beschreibbar (grüner Rahmen, dunkelgrüne Schrift) | F41: Il campo è descrivibile (cornici nere, scritta verde scuro) | G41: Field is editable (green frame, dark green text) | H41: Celda editable (borde verde, letra verde oscura) | I41: Le champ peut être décrit (cadre en vert, texte en vert foncé)
D42: =HLOOKUP($C$1,$E$1:$V$4910,ROW(D42)) -> Feld is read-only (grey frame, dark grey text) | E42: Feld ist nicht beschreibbar (grauer Rahmen, dunkelgraue Schrift) | F42: Il campo non è descrivibile (cornice grigia, scritta grigio scuro) | G42: Feld is read-only (grey frame, dark grey text) | H42: Celda protegida (borde gris, letra gris oscura) | I42: Le champ est en lecture seule (cadre gris, texte en gris foncé)
D43: =HLOOKUP($C$1,$E$1:$V$4910,ROW(D43)) -> non valid value entry (for correct calculation change value) | E43: unerlaubter Wert eingegeben (zur korrekten Berechnung Wert ändern) | F43: È stato inserito un valore non permesso (per un calcolo corretto cambiare valore) | G43: non valid value entry (for correct calculation change value) | H43: Valor erróneo (cambie el valor para realizar un cálculo correcto) | I43: Valeur saisie non valide (pour un calcul correct, changez la valeur)
D44: =HLOOKUP($C$1,$E$1:$V$4910,ROW(D44)) -> Values are not consistent | E44: fehlerhafte Eingabe | F44: fehlerhafte Eingabe | G44: Values are not consistent | H44: Los valores no son consistentes | I44: Les valeurs ne sont pas cohérentes
D45: =HLOOKUP($C$1,$E$1:$V$4910,ROW(D45)) -> The format of the numbers is usually rounded to facilitate the visualization but the numbers are not actually rounded. You may see for example that an aspect is 1 (real value 1,3) and other 1 (real value 1,4) but the sum of the two aspects is 3 (real value 2,7) | E45: Das Zahlenformat ist normalerweise gerundet, um die Darstellung zu erleichtern. Die Zahlen selbst sind aber nicht gerundet. Durch diese Darstellung kann es vorkommen, dass beispielsweise ein Aspekt mit "1" angegeben wird (der wirkliche Wert ist 1,3), ein anderer ebenfalls mit "1" (wirklicher Wert 1,4) und die Summe (2,7) mit "3" angegeben wird (1+1=3) | F45: Il formato dei numeri è arrotondato per facilitare la visualizzazione, ma i numeri non sono arrotondati. Ad esempio, potresti vedere che il valore di un aspetto è 1 (valore reale 1,3) e un altro aspetto 1 (valore reale 1,4) ma la somma tra i due aspetti è 3 (valore reale 2,7) | G45: The format of the numbers is usually rounded to facilitate the visualization but the numbers are not actually rounded. You may see for example that an aspect is 1 (real value 1,3) and other 1 (real value 1,4) but the sum of the two aspects is 3 (real value 2,7) | H45: El formato de los números suele estar redondeado para facilitar la visualización pero los números no están realmente redondeados. Puede que veas, por ejemplo, que un aspecto tiene el valor 1 (con valor real 1,3) y otro aspecto el valor 1 (con valor real 1,4), y que la suma de los dos aspectos sea 3 (que en realidad es 2,7) | I45: 0
D46: =HLOOKUP($C$1,$E$1:$V$4910,ROW(D46)) -> Please note that the format of the numbers in the matrix is rounded | E46: Bitte beachten Sie, dass die Zahlenformate in der Matrix gerundet dargestellt werden | F46: Attenzione: il format dei numeri nella matrice è arrotondato | G46: Please note that the format of the numbers in the matrix is rounded | H46: Tenga en cuenta que el formato de los números en la matriz está redondeado | I46: 0
D47: =HLOOKUP($C$1,$E$1:$V$4910,ROW(D47)) -> 0 | I47: 0
D48: =HLOOKUP($C$1,$E$1:$V$4910,ROW(D48)) -> 0 | I48: 0
D49: =HLOOKUP($C$1,$E$1:$V$4910,ROW(D49)) -> 0 | I49: 0
D50: =HLOOKUP($C$1,$E$1:$V$4910,ROW(D50)) -> 0 | I50: 0
D51: =HLOOKUP($C$1,$E$1:$V$4910,ROW(D51)) -> 0 | I51: 0
D52: =HLOOKUP($C$1,$E$1:$V$4910,ROW(D52)) -> yes | E52: ja | F52: si | G52: yes | H52: Sí | I52: oui
D53: =HLOOKUP($C$1,$E$1:$V$4910,ROW(D53)) -> no | E53: nein | F53: no | G53: no | H53: No | I53: non
D54: =HLOOKUP($C$1,$E$1:$V$4910,ROW(D54)) -> CONTACT | E54: KONTAKT | F54: CONTATTO | G54: CONTACT | H54: CONTACTO | I54: CONTACT
D55: =HLOOKUP($C$1,$E$1:$V$4910,ROW(D55)) -> Questions regarding preparation of balance sheet: beratung@gemeinwohl-oekonomie.org (GWÖ-BeraterInnen); | E55: Fragen zur Bilanz-Erstellung: beratung@gemeinwohl-oekonomie.org (GWÖ-BeraterInnen); | F55: Domande per il bilancio: info@economia-del-ben-comune.it (consulenti EBC) | G55: Questions regarding preparation of balance sheet: beratung@gemeinwohl-oekonomie.org (GWÖ-BeraterInnen); | H55: Preguntas sobre como elaborar el balance del Bien Común: nodo-empresas@economia-del-bien-comun.es | I55: Questions concernant la préparation du bilan : beratung@gemeinwohl-oekonomie.org (GWÖ-BeraterInnen);
D56: =HLOOKUP($C$1,$E$1:$V$4910,ROW(D56)) -> Questions regarding audit: audit@gemeinwohl-oekonomie.org (GWÖ-AuditorInnen); | E56: Fragen zur Auditierung: audit@gemeinwohl-oekonomie.org (GWÖ-AuditorInnen); | F56: Domande per l'audit: audit@febc.eu (Verificatori/auditori EBC) | G56: Questions regarding audit: audit@gemeinwohl-oekonomie.org (GWÖ-AuditorInnen); | H56: Preguntas sobre la auditoría: nodo-empresas@economia-del-bien-comun.es | I56: Questions concernant l'audit : audit@gemeinwohl-oekonomie.org (GWÖ-AuditorInnen);
D57: =HLOOKUP($C$1,$E$1:$V$4910,ROW(D57)) -> Feedback on the development of the Matrix: bilanz@ecogood.org (Matrix Development Team) | E57: Weiterentwicklung der Matrix: bilanz@ecogood.org (GWÖ-Matrix Entwicklungsteam); | F57: ="[it]"&E57 -> [it]Weiterentwicklung der Matrix: bilanz@ecogood.org (GWÖ-Matrix Entwicklungsteam); | G57: Feedback on the development of the Matrix: bilanz@ecogood.org (Matrix Development Team) | H57: Desarrollo de la matriz: bilanz@ecogood.org (Equipo de desarrollo de la matriz EBC) | I57: Retour d'expériences pour le développement de la matrice : bilanz@ecogood.org (GWÖ-Matrix Entwicklungsteam);
D58: =HLOOKUP($C$1,$E$1:$V$4910,ROW(D58)) -> Excel programming: Christian Loy (christian.loy@gmx.at); Christian Kozina; Multilanguage tool: Bernhard Oberrauch | E58: Excel-Programmierung: Christian Loy (christian.loy@gmx.at); Christian Kozina; Multilanguage-tool: Bernhard Oberrauch | F58: Programmazione Excel: Christian Loy (christian.loy@gmx.at); Christian Kozina; Multilanguage-tool: Bernhard Oberrauch (info@a-bo.net) | G58: Excel programming: Christian Loy (christian.loy@gmx.at); Christian Kozina; Multilanguage tool: Bernhard Oberrauch | H58: Programación en Excel: Christian Loy (christian.loy@gmx.at);Christian Kozina; Multilanguage-tool: Bernhard Oberrauch | I58: Programmation Excel : Christian Loy (christian.loy@gmx.at); Christian Kozina; Multilanguage-tool: Bernhard Oberrauch
D59: =HLOOKUP($C$1,$E$1:$V$4910,ROW(D59)) -> Contents: ECG-Matrix Development Team | E59: Inhalte: GWÖ-Matrix Entwicklungsteam | F59: ="[it]"&E59 -> [it]Inhalte: GWÖ-Matrix Entwicklungsteam | G59: Contents: ECG-Matrix Development Team | H59: Contenido: Equipo de desarrollo de la matriz EBC | I59: Contenus : MDT (ECG-Matrix Development Team)
D60: =HLOOKUP($C$1,$E$1:$V$4910,ROW(D60)) -> NOTES | E60: ANMERKUNGEN | F60: ANNOTAZIONI | G60: NOTES | H60: NOTAS ACLARATORIAS | I60: NOTES
D61: =HLOOKUP($C$1,$E$1:$V$4910,ROW(D61)) -> All sheets are optimised for printing on A4 format (landscape or portrait). The height of rows can be adjusted, if you enter more text The format of the numbers is usually rounded to facilitate the visualization but the numbers are not actually rounded. You may see as an example that an aspect is 1 (actually 1,3) and other 1 (actually 1,4) but the sum is 3 (actually 2,7). | E61: Alle Tabellen sind optimiert für den Ausdruck auf A4 (Hoch- oder Querformat). Die Höhe der Zeilen ist veränderbar, falls Sie mehr Text eingeben wollen. | F61: Tutte le tabelle sono ottimizzate per la stampa in A4 (verticale o orizzontale). L’Altezza delle celle è modificabile, nel caso Lei dovesse inserire più testo. | G61: All sheets are optimised for printing on A4 format (landscape or portrait). The height of rows can be adjusted, if you enter more text The format of the numbers is usually rounded to facilitate the visualization but the numbers are not actually rounded. You may see as an example that an aspect is 1 (actually 1,3) and other 1 (actually 1,4) but the sum is 3 (actually 2,7). | H61: Todas las hojas están optimizadas para la impresión en formato A4 (apaisado o retrato). La altura de las filas se puede ajustar, si se introduce más texto El formato de los números suele estar redondeado para facilitar la visualización, pero los números no están realmente redondeados. Puedes ver como ejemplo que un aspecto es 1 (en realidad 1,3) y otro 1 (en realidad 1,4) pero la suma es 3 (en realidad 2,7). | I61: Toutes les feuilles sont configurées pour une impression en format A4 (paysage ou portrait). La hauteur des colonnes peut être ajustée, si vous aviez besoin de plus de texte.
D62: =HLOOKUP($C$1,$E$1:$V$4910,ROW(D62)) -> GENERAL INFORMATION ABOUT THE COMPANY | E62: ALLGEMEINE ANGABEN ZUM UNTERNEHMEN | F62: Dati dell'impresa | G62: GENERAL INFORMATION ABOUT THE COMPANY | H62: INFORMACIÓN GENERAL SOBRE LA EMPRESA | I62: INFORMATIONS GENERALES SUR L'ENTREPRISE
D63: =HLOOKUP($C$1,$E$1:$V$4910,ROW(D63)) -> Please complete all fields. | E63: Bitte vollständig ausfüllen! | F63: Per favore compili completamente! | G63: Please complete all fields. | H63: Por favor introduzca todos los datos | I63: Merci de compléter tous les champs
D64: =HLOOKUP($C$1,$E$1:$V$4910,ROW(D64)) -> Name of Company / Organisation: | E64: Name des Unternehmens: | F64: Nome dell'impresa: | G64: Name of Company / Organisation: | H64: Nombre de la empresa: | I64: Nom de l'entreprise / organisation :
D65: =HLOOKUP($C$1,$E$1:$V$4910,ROW(D65)) -> Address: | E65: Anschrift: | F65: Indirizzo: | G65: Address: | H65: Dirección: | I65: Adresse :
D66: =HLOOKUP($C$1,$E$1:$V$4910,ROW(D66)) -> Country: | E66: Staat: | F66: Stato: | G66: Country: | H66: Estado: | I66: Pays :
D67: =HLOOKUP($C$1,$E$1:$V$4910,ROW(D67)) -> Industry sector: | E67: Branche: | F67: Settore: | G67: Industry sector: | H67: Sector: | I67: Secteur industriel :
D68: =HLOOKUP($C$1,$E$1:$V$4910,ROW(D68)) -> Website: | E68: Website: | F68: Sito web: | G68: Website: | H68: Página web: | I68: Site web :
D69: =HLOOKUP($C$1,$E$1:$V$4910,ROW(D69)) -> Number of employees | E69: Anzahl der MitarbeiterInnen: | F69: Presenza adetti | G69: Number of employees | H69: Número de trabajadores: | I69: Nombre d'employés :
D70: =HLOOKUP($C$1,$E$1:$V$4910,ROW(D70)) -> Sole trader (ST) (or single-person) | E70: Ein-Personen-Unternehmen: | F70: Impresa "di un collabpratore": | G70: Sole trader (ST) (or single-person) | H70: Empresas unipersonales: | I70: entreprise unipersonnelle
D71: =HLOOKUP($C$1,$E$1:$V$4910,ROW(D71)) -> (Note: If yes, the values for STs will be filled in automatically for the calculation) | E71: (Hinweis: Wenn ja, werden die für EPUs gültigen Werte automatisch in die Berechnung übernommen.) | F71: (Attenzione: se la risposta è si, I valori validi per l’impresa individuale vengono accettati automaticamente nel calcolo.) | G71: (Note: If yes, the values for STs will be filled in automatically for the calculation) | H71: (Nota: si introduce sí, entonces se aplican algunos valores automáticos en la ponderación) | I71: si oui, les données de calcul concernant les Entreprise individuelles sont automatiquement ajustées
... D83: =HLOOKUP($C$1,$E$1:$V$4910,ROW(D83)) -> Period under review | E83: Bilanz-Jahr | F83: Anno di riferimento | G83: Period under review | H83: Año del balance: | I83: Année du bilan
D84: =HLOOKUP($C$1,$E$1:$V$4910,ROW(D84)) -> 0 | I84: 0
D85: =HLOOKUP($C$1,$E$1:$V$4910,ROW(D85)) -> 0 | I85: 0
D86: =HLOOKUP($C$1,$E$1:$V$4910,ROW(D86)) -> 0 | I86: 0
D87: =HLOOKUP($C$1,$E$1:$V$4910,ROW(D87)) -> 0 | I87: 0
D88: =HLOOKUP($C$1,$E$1:$V$4910,ROW(D88)) -> 0 | I88: 0
D89: =HLOOKUP($C$1,$E$1:$V$4910,ROW(D89)) -> 0 | I89: 0
D90: =HLOOKUP($C$1,$E$1:$V$4910,ROW(D90)) -> CALCULATION OF INDIVIDUAL ASPECTS | E90: BERECHNUNG DER EINZELNEN ASPEKTE | F90: Calcolo detagliato dei singoli aspetti | G90: CALCULATION OF INDIVIDUAL ASPECTS | H90: CÁLCULO DE CADA UNO DE LOS ASPECTOS | I90: CALCUL DES ASPECTS INDIVIDUELS
D91: =HLOOKUP($C$1,$E$1:$V$4910,ROW(D91)) -> Common Good Balance Calculator | E91: Gemeinwohl-Bilanz-Rechner | F91: Calcolatore del bilancio del Bene Comune | G91: Common Good Balance Calculator | H91: Calculadora del Bien Común | I91: Calculateur du bilan de l'Economie pour le Bien Commun
D92: =HLOOKUP($C$1,$E$1:$V$4910,ROW(D92)) -> Total Balance Score: | E92: BILANZSUMME: | F92: Somma Bilancio: | G92: Total Balance Score: | H92: Puntuación total: | I92: Total score bilan :
D93: =HLOOKUP($C$1,$E$1:$V$4910,ROW(D93)) -> No. | E93: Nr. | F93: N° | G93: No. | H93: N.º | I93: N°
D94: =HLOOKUP($C$1,$E$1:$V$4910,ROW(D94)) -> Stakeholders | E94: Berührungsgruppe | F94: Gruppo coinvolto | G94: Stakeholders | H94: Grupos de interés | I94: Parties prenantes
D95: =HLOOKUP($C$1,$E$1:$V$4910,ROW(D95)) -> Stakeholders/Indicators/Criteria | E95: Berührungsgruppe/Themen/Aspekte | F95: Gruppo d'Interesse/Tema/Aspetto | G95: Stakeholders/Indicators/Criteria | H95: Grupo de interés / Tema / Aspecto | I95: Parties prenantes/thèmes/aspects
D96: =HLOOKUP($C$1,$E$1:$V$4910,ROW(D96)) -> Weight | E96: Gewichtung | F96: Peso | G96: Weight | H96: Ponderación | I96: Pondération
C97: 4 | D97: =HLOOKUP($C$1,$E$1:$V$4910,ROW(D97)) -> very high | E97: sehr hoch | F97: molto alto | G97: very high | H97: Muy alta | I97: Très haut
C98: 3 | D98: =HLOOKUP($C$1,$E$1:$V$4910,ROW(D98)) -> high | E98: hoch | F98: alto | G98: high | H98: Alta | I98: Haut
C99: 2 | D99: =HLOOKUP($C$1,$E$1:$V$4910,ROW(D99)) -> medium | E99: mittel | F99: medio | G99: medium | H99: Media | I99: Moyen
C100: 1 | D100: =HLOOKUP($C$1,$E$1:$V$4910,ROW(D100)) -> low | E100: niedrig | F100: basso | G100: low | H100: Baja | I100: Faible
C101: 0 | D101: =HLOOKUP($C$1,$E$1:$V$4910,ROW(D101)) -> not applicable | E101: trifft nicht zu | F101: non da considerare | G101: not applicable | H101: No aplica | I101: non concerné
D102: =HLOOKUP($C$1,$E$1:$V$4910,ROW(D102)) -> Current status | E102: Erläuterung | F102: Descrizione | G102: Current status | H102: Estado actual | I102: Explication
D103: =HLOOKUP($C$1,$E$1:$V$4910,ROW(D103)) -> Potential for improvement | E103: Verbesserungspotenzial | F103: Possibilità di miglioramento | G103: Potential for improvement | H103: Áreas de mejora | I103: Potentiel d'amélioration
D104: =HLOOKUP($C$1,$E$1:$V$4910,ROW(D104)) -> Est% | E104: Erfüll. | F104: Val% | G104: Est% | H104: Nivel | I104: Estimation
D105: =HLOOKUP($C$1,$E$1:$V$4910,ROW(D105)) -> Points | E105: Pkte | F105: Punti | G105: Points | H105: Punt. | I105: Points
D106: =HLOOKUP($C$1,$E$1:$V$4910,ROW(D106)) -> Max. | E106: Max. | F106: Max. | G106: Max. | H106: Max. | I106: Max.
D107: =HLOOKUP($C$1,$E$1:$V$4910,ROW(D107)) -> Stakeholders/ Themes/ Aspects | E107: Berührungsgruppe/Themen/Aspekte | F107: Stakeholders/ tematiche/ aspetti | G107: Stakeholders/ Themes/ Aspects | H107: Grupo de interés / Tema / Aspecto | I107: Parties prenantes/Thèmes/Aspects
B108: =C108&": "&D108 -> A: Suppliers | C108: A | D108: =HLOOKUP($C$1,$E$1:$V$4910,ROW(D108)) -> Suppliers | E108: Lieferant*innen | F108: Fornitori | G108: Suppliers | H108: Proveedores | I108: Les fournisseurs
B109: =C109&": "&D109 -> A1: Human dignity in the supply chain | C109: A1 | D109: =HLOOKUP($C$1,$E$1:$V$4910,ROW(D109)) -> Human dignity in the supply chain | E109: Menschenwürde in der Zulieferkette | F109: La dignità umana lungo la catena di fornitura | G109: Human dignity in the supply chain | H109: Dignidad humana en la cadena de suministro | I109: Dignité humaine dans la chaîne d'approvisionnement
C110: A1.1 | D110: =HLOOKUP($C$1,$E$1:$V$4910,ROW(D110)) -> Working conditions and social impact in the supply chain | E110: Arbeitsbedingungen und gesellschaftliche Auswirkungen in der Zulieferkette | F110: Condizioni di lavoro e conseguenze sociali nella catena di fornitura | G110: Working conditions and social impact in the supply chain | H110: Condiciones de trabajo e impacto social en la cadena de suministro | I110: Conditions de travail et impacts ou conséquences sociales dans la chaîne d’approvisionnement
C111: A1.2 | D111: =HLOOKUP($C$1,$E$1:$V$4910,ROW(D111)) -> Negative aspect: violation of human dignity in the supply chain | E111: Negativ-Aspekt: Verletzung der Menschenwürde in der Zulieferkette | F111: Aspetto negativo: Violazione della dignità umana nella catena di fornitura | G111: Negative aspect: violation of human dignity in the supply chain | H111: Aspecto negativo: vulneración de la dignidad humana en la cadena de suministro | I111: Aspect négatif : Violation de la dignité humaine dans la chaîne d'approvisionnement
B112: =C112&": "&D112 -> A2: Solidarity and social justice in the supply chain | C112: A2 | D112: =HLOOKUP($C$1,$E$1:$V$4910,ROW(D112)) -> Solidarity and social justice in the supply chain | E112: Solidarität und Gerechtigkeit in der Zulieferkette | F112: Solidarietà e giustizia nella catena di fornitura | G112: Solidarity and social justice in the supply chain | H112: Justicia y solidaridad en la cadena de suministro | I112: Solidarité et équité dans la chaîne d'approvisionnement
C113: A2.1 | D113: =HLOOKUP($C$1,$E$1:$V$4910,ROW(D113)) -> Fair business practices towards direct suppliers | E113: Faire Geschäftsbeziehungen zu direkten Lieferant*innen | F113: Relazioni commerciali eque nei confronti dei fornitori diretti | G113: Fair business practices towards direct suppliers | H113: Actitud ética con proveedores directos | I113: Relations commerciales équitables avec les fournisseurs directs
C114: A2.2 | D114: =HLOOKUP($C$1,$E$1:$V$4910,ROW(D114)) -> Exercising a positive influence on solidarity and social justice in the supply chain | E114: Positive Einflussnahme auf Solidarität und Gerechtigkeit in der gesamten Zulieferkette | F114: Influssi positivi sulla solidarietà e la giustizia lungo l'intera catena di fornitura | G114: Exercising a positive influence on solidarity and social justice in the supply chain | H114: Promoción de la justicia y la solidaridad en toda la cadena de suministro | I114: Influence positive sur la solidarité et l'équité tout au long de la chaîne d'approvisionnement
C115: A2.3 | D115: =HLOOKUP($C$1,$E$1:$V$4910,ROW(D115)) -> Negative aspect: abuse of market power against suppliers | E115: Negativ-Aspekt: Ausnutzung der Marktmacht gegenüber Lieferant*innen | F115: Aspetto negativo: Sfruttamento del potere di mercato nei confronti dei fornitori | G115: Negative aspect: abuse of market power against suppliers | H115: Aspecto negativo: abuso de poder de mercado frente a proveedores | I115: Aspect négatif : Exploiter le pouvoir de marché vis-à-vis des fournisseurs
B116: =C116&": "&D116 -> A3: Environmental sustainability in the supply chain | C116: A3 | D116: =HLOOKUP($C$1,$E$1:$V$4910,ROW(D116)) -> Environmental sustainability in the supply chain | E116: Ökologische Nachhaltigkeit in der Zulieferkette | F116: Sostenibilità ecologica nella catena di fornitura | G116: Environmental sustainability in the supply chain | H116: Sostenibilidad medioambiental en la cadena de suministro | I116: Durabilité écologique dans la chaîne d'approvisionnement
C117: A3.1 | D117: =HLOOKUP($C$1,$E$1:$V$4910,ROW(D117)) -> Environmental impact throughout the supply chain | E117: Umweltauswirkungen in der Zulieferkette | F117: Conseguenze ambientali lungo la catena di fornitura | G117: Environmental impact throughout the supply chain | H117: Impacto medioambiental en la cadena de suministro | I117: Impacts environnementaux dans la chaîne d'approvisionnement
...
